riscv-16/ALU.v
module ALU (
    input  [15:0] SrcA,
    input  [15:0] SrcB,
    input  [3:0]  ALU_control,
    output reg [15:0] ALU_result,
    output           zero
);

always @(*) begin
    case (ALU_control)
        4'b0000: ALU_result = SrcA + SrcB;                 // ADD / ADDI / Load / Store / JALR
        4'b0001: ALU_result = SrcA - SrcB;                 // SUB
        4'b0010: ALU_result = SrcA ^ SrcB;                 // XOR / XORI
        4'b0011: ALU_result = SrcA | SrcB;                 // OR / ORI
        4'b0100: ALU_result = SrcA & SrcB;                 // AND / ANDI
        4'b0101: ALU_result = SrcA << SrcB[3:0];           // SLL
        4'b0110: ALU_result = SrcA >> SrcB[3:0];           // SRL
        4'b0111: ALU_result = $signed(SrcA) >>> SrcB[3:0]; // SRA
        4'b1000: ALU_result = SrcA + 16'd2;               // JAL (PC + 2)
        default: ALU_result = 16'h0000;
    endcase
end

assign zero = (ALU_result == 16'd0);

endmodule

riscv-16/tb/ALU_tb.v
`timescale 1ns / 1ps

module ALU_tb;

    // Inputs
    reg [15:0] SrcA;
    reg [15:0] SrcB;
    reg [3:0] ALU_control;

    // Outputs
    wire [15:0] ALU_result;
    wire zero;

    // Expected result
    reg [15:0] expected;

    // Instantiate the ALU
    ALU uut (
        .SrcA(SrcA),
        .SrcB(SrcB),
        .ALU_control(ALU_control),
        .ALU_result(ALU_result),
        .zero(zero)
    );

    // For waveform generation
    initial begin
        $dumpfile("./tb/waveform/ALU.vcd");
        $dumpvars(0, ALU_tb);
    end

    initial begin
        $display("-----------------------------------------------------------------------------------------------");
        $display("| Instr  |   SrcA   |   SrcB   | ALU Ctrl | Expected  | ALU Result | Zero | Zero Correct? | Pass? |");
        $display("-----------------------------------------------------------------------------------------------");

        // ADD
        SrcA = 16'd10; SrcB = 16'd5; ALU_control = 4'b0000; expected = 10 + 5;
        #10 $display("| ADD    | %8d | %8d |   %b    | %8d | %10d |   %b  |      %s      |  %s  |",
                     SrcA, SrcB, ALU_control, expected, ALU_result, zero,
                     (zero == (expected == 0)) ? "YES" : "NO",
                     (ALU_result == expected) ? "YES" : "NO");

        // SUB
        ALU_control = 4'b0001; expected = 10 - 5;
        #10 $display("| SUB    | %8d | %8d |   %b    | %8d | %10d |   %b  |      %s      |  %s  |",
                     SrcA, SrcB, ALU_control, expected, ALU_result, zero,
                     (zero == (expected == 0)) ? "YES" : "NO",
                     (ALU_result == expected) ? "YES" : "NO");

        // XOR
        ALU_control = 4'b0010; expected = 10 ^ 5;
        #10 $display("| XOR    | %8d | %8d |   %b    | %8d | %10d |   %b  |      %s      |  %s  |",
                     SrcA, SrcB, ALU_control, expected, ALU_result, zero,
                     (zero == (expected == 0)) ? "YES" : "NO",
                     (ALU_result == expected) ? "YES" : "NO");

        // OR
        ALU_control = 4'b0011; expected = 10 | 5;
        #10 $display("| OR     | %8d | %8d |   %b    | %8d | %10d |   %b  |      %s      |  %s  |",
                     SrcA, SrcB, ALU_control, expected, ALU_result, zero,
                     (zero == (expected == 0)) ? "YES" : "NO",
                     (ALU_result == expected) ? "YES" : "NO");

        // AND
        ALU_control = 4'b0100; expected = 10 & 5;
        #10 $display("| AND    | %8d | %8d |   %b    | %8d | %10d |   %b  |      %s      |  %s  |",
                     SrcA, SrcB, ALU_control, expected, ALU_result, zero,
                     (zero == (expected == 0)) ? "YES" : "NO",
                     (ALU_result == expected) ? "YES" : "NO");

        // SLL
        SrcA = 16'd26; SrcB = 16'd3; ALU_control = 4'b0101; expected = 26 << 3;
        #10 $display("| SLL    | %8d | %8d |   %b    | %8d | %10d |   %b  |      %s      |  %s  |",
                     SrcA, SrcB, ALU_control, expected, ALU_result, zero,
                     (zero == (expected == 0)) ? "YES" : "NO",
                     (ALU_result == expected) ? "YES" : "NO");

        // SRL
        SrcA = 16'b1100_0000_0000_1111; SrcB = 16'd4; ALU_control = 4'b0110; expected = SrcA >> 4;
        #10 $display("| SRL    | %8d | %8d |   %b    | %8d | %10d |   %b  |      %s      |  %s  |",
                     SrcA, SrcB, ALU_control, expected, ALU_result, zero,
                     (zero == (expected == 0)) ? "YES" : "NO",
                     (ALU_result == expected) ? "YES" : "NO");

        // SRA
        SrcA = 16'b1000_0000_0000_1111; SrcB = 16'd4; ALU_control = 4'b0111; expected = $signed(SrcA) >>> 4;
        #10 $display("| SRA    | %8d | %8d |   %b    | %8d | %10d |   %b  |      %s      |  %s  |",
                     $signed(SrcA), SrcB, ALU_control, $signed(expected), $signed(ALU_result), zero,
                     (zero == (expected == 0)) ? "YES" : "NO",
                     ($signed(ALU_result) == $signed(expected)) ? "YES" : "NO");

        // JAL
        SrcA = 16'd100; ALU_control = 4'b1000; expected = 100 + 2;
        #10 $display("| JAL    | %8d | %8s |   %b    | %8d | %10d |   %b  |      %s      |  %s  |",
                     SrcA, "-", ALU_control, expected, ALU_result, zero,
                     (zero == (expected == 0)) ? "YES" : "NO",
                     (ALU_result == expected) ? "YES" : "NO");

        // Load/Store Address (ADD)
        SrcA = 16'd200; SrcB = 16'd12; ALU_control = 4'b0000; expected = 200 + 12;
        #10 $display("| LD/ST  | %8d | %8d |   %b    | %8d | %10d |   %b  |      %s      |  %s  |",
                     SrcA, SrcB, ALU_control, expected, ALU_result, zero,
                     (zero == (expected == 0)) ? "YES" : "NO",
                     (ALU_result == expected) ? "YES" : "NO");

        // Edge Case: zero result (SUB)
        SrcA = 16'd15; SrcB = 16'd15; ALU_control = 4'b0001; expected = 0;
        #10 $display("| SUB0   | %8d | %8d |   %b    | %8d | %10d |   %b  |      %s      |  %s  |",
                     SrcA, SrcB, ALU_control, expected, ALU_result, zero,
                     (zero == (expected == 0)) ? "YES" : "NO",
                     (ALU_result == expected) ? "YES" : "NO");

        $display("-----------------------------------------------------------------------------------------------");
        $display("ALU Test Bench Completed.");
        $finish;
    end

endmodule

riscv-16/tb/waveform/ALU.vcd
$date
	Sun Oct 19 12:47:28 2025
$end
$version
	Icarus Verilog
$end
$timescale
	1ps
$end
$scope module ALU_tb $end
$var wire 1 ! zero $end
$var wire 16 " ALU_result [15:0] $end
$var reg 4 # ALU_control [3:0] $end
$var reg 16 $ SrcA [15:0] $end
$var reg 16 % SrcB [15:0] $end
$var reg 16 & expected [15:0] $end
$scope module uut $end
$var wire 4 ' ALU_control [3:0] $end
$var wire 16 ( SrcA [15:0] $end
$var wire 16 ) SrcB [15:0] $end
$var wire 1 ! zero $end
$var reg 16 * ALU_result [15:0] $end
$upscope $end
$upscope $end
$enddefinitions $end
$comment Show the parameter values. $end
$dumpall
$end
#0
$dumpvars
b1111 *
b101 )
b1010 (
b0 '
b1111 &
b101 %
b1010 $
b0 #
b1111 "
0!
$end
#10000
b101 "
b101 *
b101 &
b1 #
b1 '
#20000
b1111 "
b1111 *
b1111 &
b10 #
b10 '
#30000
b11 #
b11 '
#40000
1!
b0 "
b0 *
b0 &
b100 #
b100 '
#50000
0!
b11010000 "
b11010000 *
b11010000 &
b101 #
b101 '
b11 %
b11 )
b11010 $
b11010 (
#60000
b110000000000 "
b110000000000 *
b110000000000 &
b110 #
b110 '
b100 %
b100 )
b1100000000001111 $
b1100000000001111 (
#70000
b1111100000000000 "
b1111100000000000 *
b1111100000000000 &
b111 #
b111 '
b1000000000001111 $
b1000000000001111 (
#80000
b1100110 "
b1100110 *
b1100110 &
b1000 #
b1000 '
b1100100 $
b1100100 (
#90000
b11010100 "
b11010100 *
b11010100 &
b0 #
b0 '
b1100 %
b1100 )
b11001000 $
b11001000 (
#100000
1!
b0 "
b0 *
b0 &
b1 #
b1 '
b1111 %
b1111 )
b1111 $
b1111 (
