riscv-16/ALU.v
module ALU (
    input  [15:0] SrcA,
    input  [15:0] SrcB,
    input  [3:0]  ALU_control,
    output reg [15:0] ALU_result,
    output           zero
);

always @(*) begin
    case (ALU_control)
        4'b0000: ALU_result = SrcA + SrcB;                 // ADD / ADDI / Load / Store / JALR
        4'b0001: ALU_result = SrcA - SrcB;                 // SUB
        4'b0010: ALU_result = SrcA ^ SrcB;                 // XOR / XORI
        4'b0011: ALU_result = SrcA | SrcB;                 // OR / ORI
        4'b0100: ALU_result = SrcA & SrcB;                 // AND / ANDI
        4'b0101: ALU_result = SrcA << SrcB[3:0];           // SLL
        4'b0110: ALU_result = SrcA >> SrcB[3:0];           // SRL
        4'b0111: ALU_result = $signed(SrcA) >>> SrcB[3:0]; // SRA
        4'b1000: ALU_result = SrcA + 16'd2;               // JAL (PC + 2)
        default: ALU_result = 16'h0000;
    endcase
end

assign zero = (ALU_result == 16'd0);

endmodule

riscv-16/tb/ALU_tb.v
`timescale 1ns / 1ps

module ALU_tb;

    // Inputs
    reg [15:0] SrcA;
    reg [15:0] SrcB;
    reg [3:0] ALU_control;

    // Outputs
    wire [15:0] ALU_result;
    wire zero;

    // Expected result
    reg [15:0] expected;

    // Instantiate the ALU
    ALU uut (
        .SrcA(SrcA),
        .SrcB(SrcB),
        .ALU_control(ALU_control),
        .ALU_result(ALU_result),
        .zero(zero)
    );

    // For waveform generation
    initial begin
        $dumpfile("./tb/waveform/ALU.vcd");
        $dumpvars(0, ALU_tb);
    end

    initial begin
        $display("-----------------------------------------------------------------------------------------------");
        $display("| Instr  |   SrcA   |   SrcB   | ALU Ctrl | Expected  | ALU Result | Zero | Zero Correct? | Pass? |");
        $display("-----------------------------------------------------------------------------------------------");

        // ADD
        SrcA = 16'd10; SrcB = 16'd5; ALU_control = 4'b0000; expected = 10 + 5;
        #10 $display("| ADD    | %8d | %8d |   %b    | %8d | %10d |   %b  |      %s      |  %s  |",
                     SrcA, SrcB, ALU_control, expected, ALU_result, zero,
                     (zero == (expected == 0)) ? "YES" : "NO",
                     (ALU_result == expected) ? "YES" : "NO");

        // SUB
        ALU_control = 4'b0001; expected = 10 - 5;
        #10 $display("| SUB    | %8d | %8d |   %b    | %8d | %10d |   %b  |      %s      |  %s  |",
                     SrcA, SrcB, ALU_control, expected, ALU_result, zero,
                     (zero == (expected == 0)) ? "YES" : "NO",
                     (ALU_result == expected) ? "YES" : "NO");

        // XOR
        ALU_control = 4'b0010; expected = 10 ^ 5;
        #10 $display("| XOR    | %8d | %8d |   %b    | %8d | %10d |   %b  |      %s      |  %s  |",
                     SrcA, SrcB, ALU_control, expected, ALU_result, zero,
                     (zero == (expected == 0)) ? "YES" : "NO",
                     (ALU_result == expected) ? "YES" : "NO");

        // OR
        ALU_control = 4'b0011; expected = 10 | 5;
        #10 $display("| OR     | %8d | %8d |   %b    | %8d | %10d |   %b  |      %s      |  %s  |",
                     SrcA, SrcB, ALU_control, expected, ALU_result, zero,
                     (zero == (expected == 0)) ? "YES" : "NO",
                     (ALU_result == expected) ? "YES" : "NO");

        // AND
        ALU_control = 4'b0100; expected = 10 & 5;
        #10 $display("| AND    | %8d | %8d |   %b    | %8d | %10d |   %b  |      %s      |  %s  |",
                     SrcA, SrcB, ALU_control, expected, ALU_result, zero,
                     (zero == (expected == 0)) ? "YES" : "NO",
                     (ALU_result == expected) ? "YES" : "NO");

        // SLL
        SrcA = 16'd26; SrcB = 16'd3; ALU_control = 4'b0101; expected = 26 << 3;
        #10 $display("| SLL    | %8d | %8d |   %b    | %8d | %10d |   %b  |      %s      |  %s  |",
                     SrcA, SrcB, ALU_control, expected, ALU_result, zero,
                     (zero == (expected == 0)) ? "YES" : "NO",
                     (ALU_result == expected) ? "YES" : "NO");

        // SRL
        SrcA = 16'b1100_0000_0000_1111; SrcB = 16'd4; ALU_control = 4'b0110; expected = SrcA >> 4;
        #10 $display("| SRL    | %8d | %8d |   %b    | %8d | %10d |   %b  |      %s      |  %s  |",
                     SrcA, SrcB, ALU_control, expected, ALU_result, zero,
                     (zero == (expected == 0)) ? "YES" : "NO",
                     (ALU_result == expected) ? "YES" : "NO");

        // SRA
        SrcA = 16'b1000_0000_0000_1111; SrcB = 16'd4; ALU_control = 4'b0111; expected = $signed(SrcA) >>> 4;
        #10 $display("| SRA    | %8d | %8d |   %b    | %8d | %10d |   %b  |      %s      |  %s  |",
                     $signed(SrcA), SrcB, ALU_control, $signed(expected), $signed(ALU_result), zero,
                     (zero == (expected == 0)) ? "YES" : "NO",
                     ($signed(ALU_result) == $signed(expected)) ? "YES" : "NO");

        // JAL
        SrcA = 16'd100; ALU_control = 4'b1000; expected = 100 + 2;
        #10 $display("| JAL    | %8d | %8s |   %b    | %8d | %10d |   %b  |      %s      |  %s  |",
                     SrcA, "-", ALU_control, expected, ALU_result, zero,
                     (zero == (expected == 0)) ? "YES" : "NO",
                     (ALU_result == expected) ? "YES" : "NO");

        // Load/Store Address (ADD)
        SrcA = 16'd200; SrcB = 16'd12; ALU_control = 4'b0000; expected = 200 + 12;
        #10 $display("| LD/ST  | %8d | %8d |   %b    | %8d | %10d |   %b  |      %s      |  %s  |",
                     SrcA, SrcB, ALU_control, expected, ALU_result, zero,
                     (zero == (expected == 0)) ? "YES" : "NO",
                     (ALU_result == expected) ? "YES" : "NO");

        // Edge Case: zero result (SUB)
        SrcA = 16'd15; SrcB = 16'd15; ALU_control = 4'b0001; expected = 0;
        #10 $display("| SUB0   | %8d | %8d |   %b    | %8d | %10d |   %b  |      %s      |  %s  |",
                     SrcA, SrcB, ALU_control, expected, ALU_result, zero,
                     (zero == (expected == 0)) ? "YES" : "NO",
                     (ALU_result == expected) ? "YES" : "NO");

        $display("-----------------------------------------------------------------------------------------------");
        $display("ALU Test Bench Completed.");
        $finish;
    end

endmodule

riscv-16/tb/waveform/ALU.vcd
$date
	Fri Jan 30 08:46:53 2026
$end
$version
	Icarus Verilog
$end
$timescale
	1ps
$end
$scope module ALU_tb $end
$var wire 1 ! zero $end
$var wire 16 " ALU_result [15:0] $end
$var reg 4 # ALU_control [3:0] $end
$var reg 16 $ SrcA [15:0] $end
$var reg 16 % SrcB [15:0] $end
$var reg 16 & expected [15:0] $end
$scope module uut $end
$var wire 4 ' ALU_control [3:0] $end
$var wire 16 ( SrcA [15:0] $end
$var wire 16 ) SrcB [15:0] $end
$var wire 1 ! zero $end
$var reg 16 * ALU_result [15:0] $end
$upscope $end
$upscope $end
$enddefinitions $end
$comment Show the parameter values. $end
$dumpall
$end
#0
$dumpvars
b1111 *
b101 )
b1010 (
b0 '
b1111 &
b101 %
b1010 $
b0 #
b1111 "
0!
$end
#10000
1!
b0 "
b0 *
b0 &
b1 %
b1 )
b1111111111111111 $
b1111111111111111 (
#20000
0!
b1000000000000000 "
b1000000000000000 *
b1000000000000000 &
b111111111111111 $
b111111111111111 (
#30000
1!
b0 "
b0 *
b0 &
b1000000000000000 %
b1000000000000000 )
b1000000000000000 $
b1000000000000000 (
#40000
0!
b1111111111111111 "
b1111111111111111 *
b1111111111111111 &
b111111111111111 %
b111111111111111 )
#50000
b101 "
b101 *
b101 &
b1 #
b1 '
b101 %
b101 )
b1010 $
b1010 (
#60000
1!
b0 "
b0 *
b0 &
b1111 %
b1111 )
b1111 $
b1111 (
#70000
0!
b1111111111111111 "
b1111111111111111 *
b1111111111111111 &
b1 %
b1 )
b0 $
b0 (
#80000
b1 "
b1 *
b1 &
b111111111111111 %
b111111111111111 )
b1000000000000000 $
b1000000000000000 (
#90000
b1111111111111111 "
b1111111111111111 *
b1111111111111111 &
b0 %
b0 )
b1111111111111111 $
b1111111111111111 (
#100000
b1 "
b1 *
b1 &
b1111111111111111 %
b1111111111111111 )
b0 $
b0 (
#110000
b1111 "
b1111 *
b1111 &
b10 #
b10 '
b101 %
b101 )
b1010 $
b1010 (
#120000
b1001000110100 "
b1001000110100 *
b1001000110100 &
b0 %
b0 )
b1001000110100 $
b1001000110100 (
#130000
b101010101010101 "
b101010101010101 *
b101010101010101 &
b1111111111111111 %
b1111111111111111 )
b1010101010101010 $
b1010101010101010 (
#140000
1!
b0 "
b0 *
b0 &
b101010110101010 %
b101010110101010 )
b101010110101010 $
b101010110101010 (
#150000
0!
b111111111111111 "
b111111111111111 *
b111111111111111 &
b1000000000000000 %
b1000000000000000 )
b1111111111111111 $
b1111111111111111 (
#160000
b1111111111111111 "
b1111111111111111 *
b1111111111111111 &
b101010101010101 %
b101010101010101 )
b1010101010101010 $
b1010101010101010 (
#170000
1!
b0 "
b0 *
b0 &
b11 #
b11 '
b0 %
b0 )
b0 $
b0 (
#180000
0!
b1111111111111111 "
b1111111111111111 *
b1111111111111111 &
b1111111111111111 %
b1111111111111111 )
#190000
b1111111111111111 $
b1111111111111111 (
#200000
b101010101010101 %
b101010101010101 )
b1010101010101010 $
b1010101010101010 (
#210000
b1000000000000000 "
b1000000000000000 *
b1000000000000000 &
b0 %
b0 )
b1000000000000000 $
b1000000000000000 (
#220000
b1 "
b1 *
b1 &
b1 $
b1 (
#230000
1!
b0 "
b0 *
b0 &
b100 #
b100 '
b0 $
b0 (
#240000
0!
b1111111111111111 "
b1111111111111111 *
b1111111111111111 &
b1111111111111111 %
b1111111111111111 )
b1111111111111111 $
b1111111111111111 (
#250000
1!
b0 "
b0 *
b0 &
b0 %
b0 )
#260000
0!
b1010010110100101 "
b1010010110100101 *
b1010010110100101 &
b1010010110100101 %
b1010010110100101 )
b1010010110100101 $
b1010010110100101 (
#270000
1!
b0 "
b0 *
b0 &
b101010101010101 %
b101010101010101 )
b1010101010101010 $
b1010101010101010 (
#280000
0!
b1000000000000000 "
b1000000000000000 *
b1000000000000000 &
b1111111111111111 %
b1111111111111111 )
b1000000000000000 $
b1000000000000000 (
#290000
b1 "
b1 *
b1 &
b1 $
b1 (
#300000
b1001000110100 "
b1001000110100 *
b1001000110100 &
b101 #
b101 '
b0 %
b0 )
b1001000110100 $
b1001000110100 (
#310000
b10 "
b10 *
b10 &
b1 %
b1 )
b1 $
b1 (
#320000
b1000000000000000 "
b1000000000000000 *
b1000000000000000 &
b1111 %
b1111 )
#330000
1!
b0 "
b0 *
b0 &
b1 %
b1 )
b1000000000000000 $
b1000000000000000 (
#340000
0!
b1000000000000000 "
b1000000000000000 *
b1000000000000000 &
b1111 %
b1111 )
b11111111 $
b11111111 (
#350000
1!
b0 "
b0 *
b0 &
b111 %
b111 )
b0 $
b0 (
#360000
0!
b110000 "
b110000 *
b110000 &
b100 %
b100 )
b11 $
b11 (
#370000
b110000000000 "
b110000000000 *
b110000000000 &
b110 #
b110 '
b1100000000001111 $
b1100000000001111 (
#380000
b11000000111001 "
b11000000111001 *
b11000000111001 &
b0 %
b0 )
b11000000111001 $
b11000000111001 (
#390000
b100000000000000 "
b100000000000000 *
b100000000000000 &
b1 %
b1 )
b1000000000000001 $
b1000000000000001 (
#400000
1!
b0 "
b0 *
b0 &
b100 %
b100 )
b1 $
b1 (
#410000
b111 %
b111 )
b0 $
b0 (
#420000
0!
b111111111111 "
b111111111111 *
b111111111111 &
b100 %
b100 )
b1111111111111111 $
b1111111111111111 (
#430000
b1 "
b1 *
b1 &
b1111 %
b1111 )
b1000000000000000 $
b1000000000000000 (
#440000
1!
b0 "
b0 *
b0 &
b111 #
b111 '
b100 %
b100 )
b0 $
b0 (
#450000
0!
b1111100000000000 "
b1111100000000000 *
b1111100000000000 &
b1000000000000000 $
b1000000000000000 (
#460000
1!
b0 "
b0 *
b0 &
b1 %
b1 )
b1 $
b1 (
#470000
0!
b1111111111111111 "
b1111111111111111 *
b1111111111111111 &
b100 %
b100 )
b1111111111111111 $
b1111111111111111 (
#480000
b1101010101010101 "
b1101010101010101 *
b1101010101010101 &
b1 %
b1 )
b1010101010101010 $
b1010101010101010 (
#490000
b1100110 "
b1100110 *
b1100110 &
b1000 #
b1000 '
b1100100 $
b1100100 (
#500000
b10 "
b10 *
b10 &
b0 $
b0 (
#510000
b1 "
b1 *
b1 &
b1111111111111111 $
b1111111111111111 (
#520000
b1000000000000001 "
b1000000000000001 *
b1000000000000001 &
b111111111111111 $
b111111111111111 (
