riscv-16/control_unit.v
`timescale 1ns / 1ps

module Control_Unit(
    input  [2:0] opcode,      // primary opcode
    input  [3:0] func,        // function field (R-type, I-type)
    input        zero,        // ALU zero flag (for branches)
    output reg        PCSrc,        // PC source select
    output reg        ResultSrc,    // result source select
    output reg        MemWrite,     // memory write enable
    output reg  [3:0] ALUControl,   // ALU operation select
    output reg        ALUSrc,       // ALU source select
    output reg  [1:0] ImmSrc,       // immediate type select
    output reg        RegWrite      // register file write enable
);

    always @(*) begin
        // Default values (NOP-safe)
        PCSrc      = 1'b0;
        ResultSrc  = 1'b0;
        MemWrite   = 1'b0;
        ALUControl = 4'b0000;
        ALUSrc     = 1'b0;
        ImmSrc     = 2'b00;
        RegWrite   = 1'b0;

        case (opcode)

            // ------------------------------------------------
            // R-type: opcode = 000
            // ------------------------------------------------
            3'b000: begin
                RegWrite   = 1'b1;
                ALUSrc     = 1'b0;
                ResultSrc  = 1'b0;
                ALUControl = func; // func directly controls ALU op
            end

            // ------------------------------------------------
            // I-type: opcode = 001
            // (addi/xori/ori/andi/jalr)
            // ------------------------------------------------
            3'b001: begin
                ALUSrc     = 1'b1;
                RegWrite   = 1'b1;
                ResultSrc  = 1'b0;
                ImmSrc     = 2'b00;

                // Decode func field
                case (func)
                    4'b0000: ALUControl = 4'b0000; // ADDI
                    4'b0001: ALUControl = 4'b0010; // XORI
                    4'b0010: ALUControl = 4'b0011; // ORI
                    4'b0011: ALUControl = 4'b0100; // ANDI
                    4'b1101: begin                  // JALR
                                ALUControl = 4'b0000; // ALU does addition (rs1 + imm)
                                ImmSrc     = 2'b00;
                                PCSrc      = 1'b1;
                            end
                    default: ALUControl = 4'b0000;
                endcase
            end

            // ------------------------------------------------
            // LW: opcode = 010
            // ------------------------------------------------
            3'b010: begin
                ALUSrc     = 1'b1;
                RegWrite   = 1'b1;
                ResultSrc  = 1'b1; // writeback from memory
                ALUControl = 4'b0000; // ADD base + offset
                ImmSrc     = 2'b00;
            end

            // ------------------------------------------------
            // SW: opcode = 011
            // ------------------------------------------------
            3'b011: begin
                ALUSrc     = 1'b1;
                MemWrite   = 1'b1;
                ALUControl = 4'b0000; // ADD base + offset
                ImmSrc     = 2'b00;
            end

            // ------------------------------------------------
            // Branches: opcode = 100
            // func = 000 (BEQ), 001 (BNE)
            // ------------------------------------------------
            3'b100: begin
                ALUSrc     = 1'b0;
                ALUControl = 4'b0001; // SUB for comparison
                ImmSrc     = 2'b01;
                RegWrite   = 1'b0;

                // Branch condition
                case (func[0])
                    1'b0: PCSrc = (zero) ? 1'b1 : 1'b0;  // BEQ
                    1'b1: PCSrc = (~zero) ? 1'b1 : 1'b0; // BNE
                endcase
            end

            // ------------------------------------------------
            // JAL: opcode = 101
            // ------------------------------------------------
            3'b101: begin
                PCSrc      = 1'b1;
                RegWrite   = 1'b1;
                ALUSrc     = 1'b1;
                ALUControl = 4'b0000; // Add PC + imm
                ImmSrc     = 2'b10;
                ResultSrc  = 1'b0;
            end

            // ------------------------------------------------
            // Default (NOP)
            // ------------------------------------------------
            default: begin
                PCSrc      = 1'b0;
                ResultSrc  = 1'b0;
                MemWrite   = 1'b0;
                ALUControl = 4'b0000;
                ALUSrc     = 1'b0;
                ImmSrc     = 2'b00;
                RegWrite   = 1'b0;
            end
        endcase
    end
endmodule

riscv-16/tb/Control_unit_tb.v
`timescale 1ns / 1ps

module Control_Unit_tb;

    // Inputs
    reg [2:0] opcode;
    reg [3:0] func;
    reg       zero;
    reg       clk;

    // Outputs
    wire PCSrc;
    wire ResultSrc;
    wire MemWrite;
    wire [3:0] ALUControl;
    wire ALUSrc;
    wire [1:0] ImmSrc;
    wire RegWrite;

    // Instantiate DUT
    Control_Unit uut (
        .opcode(opcode),
        .func(func),
        .zero(zero),
        .PCSrc(PCSrc),
        .ResultSrc(ResultSrc),
        .MemWrite(MemWrite),
        .ALUControl(ALUControl),
        .ALUSrc(ALUSrc),
        .ImmSrc(ImmSrc),
        .RegWrite(RegWrite)
    );

    // Clock generation (10ns period)
    always #5 clk = ~clk;

    // Waveform dump
    initial begin
        $dumpfile("./waveform/Control_unit.vcd");
        $dumpvars(0, Control_Unit_tb);
    end

    // Display header
    initial begin
        $display("==================================================================================================================");
        $display("Time | Opcode | Func | Zero | PCSrc | ResultSrc | MemWrite | ALUControl | ALUSrc | ImmSrc | RegWrite | Instruction");
        $display("==================================================================================================================");
    end

    // Task to show signals and check expected outputs
    task show_ctrl;
        input [255:0] instr_name;
        input exp_PCSrc, exp_ResultSrc, exp_MemWrite;
        input [3:0] exp_ALUControl;
        input exp_ALUSrc;
        input [1:0] exp_ImmSrc;
        input exp_RegWrite;
        reg pass;
        begin
            #1;
            $display("%4t |  %03b   | %04b |  %b   |   %b   |     %b     |    %b     |   %04b     |   %b   |   %02b   |    %b     | %s",
                     $time, opcode, func, zero, PCSrc, ResultSrc, MemWrite,
                     ALUControl, ALUSrc, ImmSrc, RegWrite, instr_name);

            pass = (PCSrc === exp_PCSrc) && (ResultSrc === exp_ResultSrc) && 
                   (MemWrite === exp_MemWrite) && (ALUControl === exp_ALUControl) &&
                   (ALUSrc === exp_ALUSrc) && (ImmSrc === exp_ImmSrc) &&
                   (RegWrite === exp_RegWrite);

            if (pass)
                $display("Result: \033[32mPASSED\033[0m\n");   // Green
            else
                $display("Result: \033[31mFAILED\033[0m\n");   // Red
        end
    endtask

    // Stimulus
    initial begin
        clk = 0;
        opcode = 3'b000;
        func   = 4'b0000;
        zero   = 0;

        // --- R-type instructions ---
        @(posedge clk); opcode = 3'b000; func = 4'b0000; show_ctrl("ADD", 0,0,0,4'b0000,0,2'b00,1);
        @(posedge clk); opcode = 3'b000; func = 4'b0001; show_ctrl("SUB", 0,0,0,4'b0001,0,2'b00,1);
        @(posedge clk); opcode = 3'b000; func = 4'b0010; show_ctrl("XOR", 0,0,0,4'b0010,0,2'b00,1);
        @(posedge clk); opcode = 3'b000; func = 4'b0011; show_ctrl("OR", 0,0,0,4'b0011,0,2'b00,1);
        @(posedge clk); opcode = 3'b000; func = 4'b0100; show_ctrl("AND", 0,0,0,4'b0100,0,2'b00,1);
        @(posedge clk); opcode = 3'b000; func = 4'b0101; show_ctrl("SLL", 0,0,0,4'b0101,0,2'b00,1);

        // --- I-type instructions ---
        @(posedge clk); opcode = 3'b001; func = 4'b0000; show_ctrl("ADDI", 0,0,0,4'b0000,1,2'b00,1);
        @(posedge clk); opcode = 3'b001; func = 4'b0001; show_ctrl("XORI", 0,0,0,4'b0010,1,2'b00,1);
        @(posedge clk); opcode = 3'b001; func = 4'b0010; show_ctrl("ORI", 0,0,0,4'b0011,1,2'b00,1);
        @(posedge clk); opcode = 3'b001; func = 4'b0011; show_ctrl("ANDI", 0,0,0,4'b0100,1,2'b00,1);
        @(posedge clk); opcode = 3'b001; func = 4'b1101; show_ctrl("JALR", 1,0,0,4'b0000,1,2'b00,1);

        // --- Load/Store ---
        @(posedge clk); opcode = 3'b010; func = 4'b0000; show_ctrl("LW", 0,1,0,4'b0000,1,2'b00,1);
        @(posedge clk); opcode = 3'b011; func = 4'b0000; show_ctrl("SW", 0,0,1,4'b0000,1,2'b00,0);

        // --- Branches ---
        @(posedge clk); zero = 1; opcode = 3'b100; func = 4'b0000; show_ctrl("BEQ (taken)", 1,0,0,4'b0001,0,2'b01,0);
        @(posedge clk); zero = 0; opcode = 3'b100; func = 4'b0000; show_ctrl("BEQ (not taken)", 0,0,0,4'b0001,0,2'b01,0);
        @(posedge clk); zero = 1; opcode = 3'b100; func = 4'b0001; show_ctrl("BNE (not taken)", 0,0,0,4'b0001,0,2'b01,0);
        @(posedge clk); zero = 0; opcode = 3'b100; func = 4'b0001; show_ctrl("BNE (taken)", 1,0,0,4'b0001,0,2'b01,0);

        // --- JAL ---
        @(posedge clk); opcode = 3'b101; func = 4'b0000; show_ctrl("JAL", 1,0,0,4'b0000,1,2'b10,1);

        @(posedge clk);
        $display("==================================================================================================================");
        $finish;
    end

endmodule

riscv-16/tb/waveform/control_unit.vcd
$date
	Sat Oct 18 14:54:32 2025
$end
$version
	Icarus Verilog
$end
$timescale
	1ps
$end
$scope module Control_Unit_tb $end
$var wire 1 ! ResultSrc $end
$var wire 1 " RegWrite $end
$var wire 1 # PCSrc $end
$var wire 1 $ MemWrite $end
$var wire 2 % ImmSrc [1:0] $end
$var wire 1 & ALUSrc $end
$var wire 4 ' ALUControl [3:0] $end
$var reg 1 ( clk $end
$var reg 4 ) func [3:0] $end
$var reg 3 * opcode [2:0] $end
$var reg 1 + zero $end
$scope module uut $end
$var wire 4 , func [3:0] $end
$var wire 3 - opcode [2:0] $end
$var wire 1 + zero $end
$var reg 4 . ALUControl [3:0] $end
$var reg 1 & ALUSrc $end
$var reg 2 / ImmSrc [1:0] $end
$var reg 1 $ MemWrite $end
$var reg 1 # PCSrc $end
$var reg 1 " RegWrite $end
$var reg 1 ! ResultSrc $end
$upscope $end
$scope task show_ctrl $end
$var reg 4 0 exp_ALUControl [3:0] $end
$var reg 1 1 exp_ALUSrc $end
$var reg 2 2 exp_ImmSrc [1:0] $end
$var reg 1 3 exp_MemWrite $end
$var reg 1 4 exp_PCSrc $end
$var reg 1 5 exp_RegWrite $end
$var reg 1 6 exp_ResultSrc $end
$var reg 256 7 instr_name [255:0] $end
$var reg 1 8 pass $end
$upscope $end
$upscope $end
$enddefinitions $end
$comment Show the parameter values. $end
$dumpall
$end
#0
$dumpvars
x8
bx 7
x6
x5
x4
x3
bx 2
x1
bx 0
b0 /
b0 .
b0 -
b0 ,
0+
b0 *
b0 )
0(
b0 '
0&
b0 %
0$
0#
1"
0!
$end
#5000
15
b0 2
01
b0 0
03
06
04
b10000010100010001000100 7
1(
#6000
18
#10000
0(
#15000
b1 '
b1 .
1"
b1 0
b10100110101010101000010 7
b1 )
b1 ,
1(
#20000
0(
#25000
1"
b10 '
b10 .
b10 0
b10110000100111101010010 7
b10 )
b10 ,
1(
#30000
0(
#35000
1"
b11 '
b11 .
b11 0
b100111101010010 7
b11 )
b11 ,
1(
#40000
0(
#45000
1"
b100 '
b100 .
b100 0
b10000010100111001000100 7
b100 )
b100 ,
1(
#50000
0(
#55000
1"
b101 '
b101 .
b101 0
b10100110100110001001100 7
b101 )
b101 ,
1(
#60000
0(
#65000
1&
1"
b0 '
b0 .
11
b0 0
b1000001010001000100010001001001 7
b0 )
b0 ,
b1 *
b1 -
1(
#70000
0(
#75000
b10 '
b10 .
1"
1&
b10 0
b1011000010011110101001001001001 7
b1 )
b1 ,
1(
#80000
0(
#85000
1"
1&
b11 '
b11 .
b11 0
b10011110101001001001001 7
b10 )
b10 ,
1(
#90000
0(
#95000
1"
1&
b100 '
b100 .
b100 0
b1000001010011100100010001001001 7
b11 )
b11 ,
1(
#100000
0(
#105000
1#
1"
1&
b0 '
b0 .
b0 0
14
b1001010010000010100110001010010 7
b1101 )
b1101 ,
1(
#110000
0(
#115000
1!
1"
1&
0#
16
04
b100110001010111 7
b0 )
b0 ,
b10 *
b10 -
1(
#120000
0(
#125000
1$
0"
1&
0!
05
13
06
b101001101010111 7
b11 *
b11 -
1(
#130000
0(
#135000
1#
b1 %
b1 /
b1 '
b1 .
0&
0$
b1 2
01
b1 0
03
14
b100001001000101010100010010000000101000011101000110000101101011011001010110111000101001 7
b100 *
b100 -
1+
1(
#140000
0(
#145000
b1 %
b1 /
b1 '
b1 .
0#
04
b10000100100010101010001001000000010100001101110011011110111010000100000011101000110000101101011011001010110111000101001 7
0+
1(
#150000
0(
#155000
b1 %
b1 /
b1 '
b1 .
b10000100100111001000101001000000010100001101110011011110111010000100000011101000110000101101011011001010110111000101001 7
b1 )
b1 ,
1+
1(
#160000
0(
#165000
1#
b1 %
b1 /
b1 '
b1 .
14
b100001001001110010001010010000000101000011101000110000101101011011001010110111000101001 7
0+
1(
#170000
0(
#175000
1&
1"
b10 %
b10 /
b0 '
b0 .
1#
15
b10 2
11
b0 0
b10010100100000101001100 7
b0 )
b0 ,
b101 *
b101 -
1(
