riscv-16/PC_Counter.v
`timescale 1ns / 1ps

module pc_counter_16 (
    input              clk,
    input              reset,
    input              pc_en,           // enable (for stalls)

    // Branch control (B-type, opcode=011)
    input              branch_taken,
    input signed [6:0] branch_imm,     // signed halfword offset from B-type [2]

    // JAL (J-type, opcode=101)
    input              jal_taken,
    input signed [9:0] jal_imm,        // signed halfword offset from J-type [2]

    // JALR (I-type, func=1101)
    input              jalr_taken,
    input      [15:0]  jalr_target,    // rs1 + imm (byte address)

    output reg [15:0]  pc
);
    // Convert halfword offsets to byte addresses
    function [15:0] hw_to_bytes;
        input signed [15:0] imm_hw;
        begin
            hw_to_bytes = imm_hw << 1;
        end
    endfunction

    always @(posedge clk or posedge reset) begin
        if (reset) begin
            pc <= 16'h0000;
        end else if (pc_en) begin
            if (jalr_taken) begin
                // JALR: PC = rs1 + imm, align to 2-byte boundary [1]
                pc <= {jalr_target[15:1], 1'b0};
            end else if (jal_taken) begin
                // JAL: PC += imm (halfwords → bytes), rd = PC+2 in WB [1]
                pc <= pc + hw_to_bytes({{6{jal_imm[9]}}, jal_imm});
            end else if (branch_taken) begin
                // Branch: PC += imm (halfwords → bytes) [2]
                pc <= pc + hw_to_bytes({{9{branch_imm[6]}}, branch_imm});
            end else begin
                // Sequential: next 16-bit instruction
                pc <= pc + 16'd2;
            end
        end
    end
endmodule

riscv-16/tb/PC_counter_tb.v
`timescale 1ns / 1ps

module PC_counter_tb;

    // Inputs
    reg clk;
    reg reset;
    reg pc_en;
    reg branch_taken;
    reg signed [6:0] branch_imm;
    reg jal_taken;
    reg signed [9:0] jal_imm;
    reg jalr_taken;
    reg [15:0] jalr_target;
    
    // Output
    wire [15:0] pc;

    // Instantiate PC counter
    pc_counter_16 uut (
        .clk(clk),
        .reset(reset),
        .pc_en(pc_en),
        .branch_taken(branch_taken),
        .branch_imm(branch_imm),
        .jal_taken(jal_taken),
        .jal_imm(jal_imm),
        .jalr_taken(jalr_taken),
        .jalr_target(jalr_target),
        .pc(pc)
    );

    // Clock generation (10ns period = 100 MHz)
    initial begin
        clk = 0;
        forever #5 clk = ~clk;
    end

    // Helper task to print table rows
    task print_row;
        input [63:0] time_val;
        input [15:0] pc_val;
        input [127:0] operation;
        input pass_fail;  // 0=normal, 1=PASS, 2=FAIL
        begin
            if (pass_fail == 1)
                $display("| %6d | 0x%04h | %-35s | PASS |", time_val, pc_val, operation);
            else if (pass_fail == 2)
                $display("| %6d | 0x%04h | %-35s | FAIL |", time_val, pc_val, operation);
            else
                $display("| %6d | 0x%04h | %-35s |      |", time_val, pc_val, operation);
        end
    endtask

    task print_separator;
        begin
            $display("+--------+--------+-------------------------------------+------+");
        end
    endtask

    task print_header;
        input [255:0] title;
        begin
            $display("\n+--------+--------+-------------------------------------+------+");
            $display("|                     %-43s |", title);
            print_separator();
            $display("|  Time  |   PC   |             Operation               |Status|");
            print_separator();
        end
    endtask

    // Test sequence
    initial begin
        // Waveform dump
        $dumpfile("./tb/waveform/PC_counter.vcd");
        $dumpvars(0, PC_counter_tb);

        // Initialize all inputs
        reset = 1;
        pc_en = 0;
        branch_taken = 0;
        branch_imm = 7'd0;
        jal_taken = 0;
        jal_imm = 10'd0;
        jalr_taken = 0;
        jalr_target = 16'h0000;

        // Wait for reset to stabilize
        #12;
        @(negedge clk);
        reset = 0;
        pc_en = 1;
        
        // Wait one full cycle after reset deassertion
        @(posedge clk);
        @(posedge clk);
        #1;

        // Test 1: Sequential increment
        print_header("Test 1: Sequential Increment (PC += 2)");
        repeat(8) begin
            print_row($time, pc, "Sequential", 0);
            @(posedge clk);
            #1;
        end
        print_separator();

        // Test 2: Branch forward
        print_header("Test 2: Branch Forward (+10 bytes)");
        $display("| Current PC before branch: 0x%04h                              |", pc);
        print_separator();
        @(negedge clk);
        branch_taken = 1;
        branch_imm = 7'sd5;
        @(posedge clk);
        #1;
        print_row($time, pc, "Branch taken (+10 bytes)", 0);
        branch_taken = 0;
        repeat(3) begin
            @(posedge clk);
            #1;
            print_row($time, pc, "Sequential", 0);
        end
        print_separator();

        // Test 3: Branch backward
        print_header("Test 3: Branch Backward (-8 bytes)");
        $display("| Current PC before branch: 0x%04h                              |", pc);
        print_separator();
        @(negedge clk);
        branch_taken = 1;
        branch_imm = -7'sd4;
        @(posedge clk);
        #1;
        print_row($time, pc, "Branch taken (-8 bytes)", 0);
        branch_taken = 0;
        repeat(3) begin
            @(posedge clk);
            #1;
            print_row($time, pc, "Sequential", 0);
        end
        print_separator();

        // Test 4: JAL forward
        print_header("Test 4: JAL Forward (+16 bytes)");
        $display("| Current PC before JAL: 0x%04h                                 |", pc);
        print_separator();
        @(negedge clk);
        jal_taken = 1;
        jal_imm = 10'sd8;
        @(posedge clk);
        #1;
        print_row($time, pc, "JAL taken (+16 bytes)", 0);
        jal_taken = 0;
        repeat(3) begin
            @(posedge clk);
            #1;
            print_row($time, pc, "Sequential", 0);
        end
        print_separator();

        // Test 5: JAL backward
        print_header("Test 5: JAL Backward (-12 bytes)");
        $display("| Current PC before JAL: 0x%04h                                 |", pc);
        print_separator();
        @(negedge clk);
        jal_taken = 1;
        jal_imm = -10'sd6;
        @(posedge clk);
        #1;
        print_row($time, pc, "JAL taken (-12 bytes)", 0);
        jal_taken = 0;
        repeat(3) begin
            @(posedge clk);
            #1;
            print_row($time, pc, "Sequential", 0);
        end
        print_separator();

        // Test 6: JALR absolute
        print_header("Test 6: JALR to 0x0100");
        $display("| Current PC before JALR: 0x%04h                                |", pc);
        print_separator();
        @(negedge clk);
        jalr_taken = 1;
        jalr_target = 16'h0100;
        @(posedge clk);
        #1;
        print_row($time, pc, "JALR to 0x0100", 0);
        jalr_taken = 0;
        repeat(3) begin
            @(posedge clk);
            #1;
            print_row($time, pc, "Sequential", 0);
        end
        print_separator();

        // Test 7: JALR unaligned
        print_header("Test 7: JALR Unaligned (0x0055 -> 0x0054)");
        $display("| Current PC before JALR: 0x%04h                                |", pc);
        print_separator();
        @(negedge clk);
        jalr_taken = 1;
        jalr_target = 16'h0055;
        @(posedge clk);
        #1;
        if (pc == 16'h0054)
            print_row($time, pc, "JALR aligned correctly", 1);
        else
            print_row($time, pc, "JALR alignment FAILED", 2);
        jalr_taken = 0;
        repeat(2) begin
            @(posedge clk);
            #1;
            print_row($time, pc, "Sequential", 0);
        end
        print_separator();

        // Test 8: PC stall
        print_header("Test 8: PC Stall (pc_en = 0)");
        $display("| Current PC: 0x%04h                                            |", pc);
        print_separator();
        @(negedge clk);
        pc_en = 0;
        repeat(5) begin
            @(posedge clk);
            #1;
            print_row($time, pc, "PC stalled", 0);
        end
        print_separator();
        
        // Resume
        $display("\n| Resuming PC (pc_en = 1)                                          |");
        print_separator();
        @(negedge clk);
        pc_en = 1;
        repeat(3) begin
            @(posedge clk);
            #1;
            print_row($time, pc, "Sequential", 0);
        end
        print_separator();

        // Test 9: Reset
        print_header("Test 9: Reset");
        $display("| Current PC before reset: 0x%04h                               |", pc);
        print_separator();
        @(negedge clk);
        reset = 1;
        @(posedge clk);
        #1;
        print_row($time, pc, "Reset asserted", 0);
        
        @(negedge clk);
        reset = 0;
        @(posedge clk);
        #1;
        if (pc == 16'h0000)
            print_row($time, pc, "PC at 0x0000 after reset", 1);
        else
            print_row($time, pc, "Reset verification", 2);
        
        repeat(3) begin
            @(posedge clk);
            #1;
            print_row($time, pc, "Sequential after reset", 0);
        end
        print_separator();

        // Test 10: Priority
        print_header("Test 10: Priority (JALR > JAL > Branch)");
        @(negedge clk);
        branch_taken = 1;
        branch_imm = 7'sd2;
        jal_taken = 1;
        jal_imm = 10'sd4;
        jalr_taken = 1;
        jalr_target = 16'h0200;
        @(posedge clk);
        #1;
        if (pc == 16'h0200)
            print_row($time, pc, "JALR priority correct", 1);
        else
            print_row($time, pc, "Priority test FAILED", 2);
        branch_taken = 0;
        jal_taken = 0;
        jalr_taken = 0;
        print_separator();

        // End
        #50;
        $display("\n+========================================+");
        $display("|     PC Counter Test Complete           |");
        $display("+========================================+\n");
        $finish;
    end

    // Timeout watchdog
    initial begin
        #10000;
        $display("\nERROR: Testbench timeout!");
        $finish;
    end

endmodule

riscv-16/tb/waveform/PC_counter.vcd
$date
	Sun Oct 19 13:09:04 2025
$end
$version
	Icarus Verilog
$end
$timescale
	1ps
$end
$scope module PC_counter_tb $end
$var wire 16 ! pc [15:0] $end
$var reg 7 " branch_imm [6:0] $end
$var reg 1 # branch_taken $end
$var reg 1 $ clk $end
$var reg 10 % jal_imm [9:0] $end
$var reg 1 & jal_taken $end
$var reg 1 ' jalr_taken $end
$var reg 16 ( jalr_target [15:0] $end
$var reg 1 ) pc_en $end
$var reg 1 * reset $end
$scope module uut $end
$var wire 7 + branch_imm [6:0] $end
$var wire 1 # branch_taken $end
$var wire 1 $ clk $end
$var wire 10 , jal_imm [9:0] $end
$var wire 1 & jal_taken $end
$var wire 1 ' jalr_taken $end
$var wire 16 - jalr_target [15:0] $end
$var wire 1 ) pc_en $end
$var wire 1 * reset $end
$var reg 16 . pc [15:0] $end
$scope function hw_to_bytes $end
$var reg 16 / imm_hw [15:0] $end
$upscope $end
$upscope $end
$scope task print_header $end
$var reg 256 0 title [255:0] $end
$upscope $end
$scope task print_row $end
$var reg 128 1 operation [127:0] $end
$var reg 1 2 pass_fail $end
$var reg 16 3 pc_val [15:0] $end
$var reg 64 4 time_val [63:0] $end
$upscope $end
$scope task print_separator $end
$upscope $end
$upscope $end
$enddefinitions $end
$comment Show the parameter values. $end
$dumpall
$end
#0
$dumpvars
bx 4
bx 3
x2
bx 1
bx 0
bx /
b0 .
b0 -
b0 ,
b0 +
1*
0)
b0 (
0'
0&
b0 %
0$
0#
b0 "
b0 !
$end
#5000
1$
#10000
0$
#15000
1$
#20000
1)
0*
0$
#25000
b10 !
b10 .
1$
#30000
0$
#35000
b100 !
b100 .
1$
#36000
02
b1010011011001010111000101110101011001010110111001110100011010010110000101101100 1
b100 3
b100100 4
b11101000100000010100110110010101110001011101010110010101101110011101000110100101100001011011000010000001001001011011100110001101110010011001010110110101100101011011100111010000100000001010000101000001000011001000000010101100111101001000000011001000101001 0
#40000
0$
#45000
b110 !
b110 .
1$
#46000
b110 3
b101110 4
#50000
0$
#55000
b1000 !
b1000 .
1$
#56000
b1000 3
b111000 4
#60000
0$
#65000
b1010 !
b1010 .
1$
#66000
b1010 3
b1000010 4
#70000
0$
#75000
b1100 !
b1100 .
1$
#76000
b1100 3
b1001100 4
#80000
0$
#85000
b1110 !
b1110 .
1$
#86000
b1110 3
b1010110 4
#90000
0$
#95000
b10000 !
b10000 .
1$
#96000
b10000 3
b1100000 4
#100000
0$
#105000
b10010 !
b10010 .
1$
#106000
b10010 3
b1101010 4
#110000
0$
#115000
b10100 !
b10100 .
1$
#116000
b111001101110100001000000011001000111010001000000100001001110010011000010110111001100011011010000010000001000110011011110111001001110111011000010111001001100100001000000010100000101011001100010011000000100000011000100111100101110100011001010111001100101001 0
#120000
b101 "
b101 +
1#
0$
#125000
b11110 !
b11110 .
b101 /
1$
#126000
0#
b1100001011010110110010101101110001000000010100000101011001100010011000000100000011000100111100101110100011001010111001100101001 1
b11110 3
b1111110 4
#130000
0$
#135000
b100000 !
b100000 .
1$
#136000
b1010011011001010111000101110101011001010110111001110100011010010110000101101100 1
b100000 3
b10001000 4
#140000
0$
#145000
b100010 !
b100010 .
1$
#146000
b100010 3
b10010010 4
#150000
0$
#155000
b100100 !
b100100 .
1$
#156000
b111001101110100001000000011001100111010001000000100001001110010011000010110111001100011011010000010000001000010011000010110001101101011011101110110000101110010011001000010000000101000001011010011100000100000011000100111100101110100011001010111001100101001 0
b100100 3
b10011100 4
#160000
b1111100 "
b1111100 +
1#
0$
#165000
b11100 !
b11100 .
b1111111111111100 /
1$
#166000
0#
b1110100011000010110101101100101011011100010000000101000001011010011100000100000011000100111100101110100011001010111001100101001 1
b11100 3
b10100110 4
#170000
0$
#175000
b11110 !
b11110 .
1$
#176000
b1010011011001010111000101110101011001010110111001110100011010010110000101101100 1
b11110 3
b10110000 4
#180000
0$
#185000
b100000 !
b100000 .
1$
#186000
b100000 3
b10111010 4
#190000
0$
#195000
b100010 !
b100010 .
1$
#196000
b1010100011001010111001101110100001000000011010000111010001000000100101001000001010011000010000001000110011011110111001001110111011000010111001001100100001000000010100000101011001100010011011000100000011000100111100101110100011001010111001100101001 0
b100010 3
b11000100 4
#200000
b1000 %
b1000 ,
1&
0$
#205000
b110010 !
b110010 .
b1000 /
1$
#206000
0&
b1100001011010110110010101101110001000000010100000101011001100010011011000100000011000100111100101110100011001010111001100101001 1
b110010 3
b11001110 4
#210000
0$
#215000
b110100 !
b110100 .
1$
#216000
b1010011011001010111000101110101011001010110111001110100011010010110000101101100 1
b110100 3
b11011000 4
#220000
0$
#225000
b110110 !
b110110 .
1$
#226000
b110110 3
b11100010 4
#230000
0$
#235000
b111000 !
b111000 .
1$
#236000
b101010001100101011100110111010000100000001101010011101000100000010010100100000101001100001000000100001001100001011000110110101101110111011000010111001001100100001000000010100000101101001100010011001000100000011000100111100101110100011001010111001100101001 0
b111000 3
b11101100 4
#240000
b1111111010 %
b1111111010 ,
1&
0$
#245000
b101100 !
b101100 .
b1111111111111010 /
1$
#246000
0&
b1100001011010110110010101101110001000000010100000101101001100010011001000100000011000100111100101110100011001010111001100101001 1
b101100 3
b11110110 4
#250000
0$
#255000
b101110 !
b101110 .
1$
#256000
b1010011011001010111000101110101011001010110111001110100011010010110000101101100 1
b101110 3
b100000000 4
#260000
0$
#265000
b110000 !
b110000 .
1$
#266000
b110000 3
b100001010 4
#270000
0$
#275000
b110010 !
b110010 .
1$
#276000
b1010100011001010111001101110100001000000011011000111010001000000100101001000001010011000101001000100000011101000110111100100000001100000111100000110000001100010011000000110000 0
b110010 3
b100010100 4
#280000
b100000000 (
b100000000 -
1'
0$
#285000
b100000000 !
b100000000 .
1$
#286000
0'
b100101001000001010011000101001000100000011101000110111100100000001100000111100000110000001100010011000000110000 1
b100000000 3
b100011110 4
#290000
0$
#295000
b100000010 !
b100000010 .
1$
#296000
b1010011011001010111000101110101011001010110111001110100011010010110000101101100 1
b100000010 3
b100101000 4
#300000
0$
#305000
b100000100 !
b100000100 .
1$
#306000
b100000100 3
b100110010 4
#310000
0$
#315000
b100000110 !
b100000110 .
1$
#316000
b100000101001100010100100010000001010101011011100110000101101100011010010110011101101110011001010110010000100000001010000011000001111000001100000011000000110101001101010010000000101101001111100010000000110000011110000011000000110000001101010011010000101001 0
b100000110 3
b100111100 4
#320000
b1010101 (
b1010101 -
1'
0$
#325000
b1010100 !
b1010100 .
1$
#326000
0'
12
b1101100011010010110011101101110011001010110010000100000011000110110111101110010011100100110010101100011011101000110110001111001 1
b1010100 3
b101000110 4
#330000
0$
#335000
b1010110 !
b1010110 .
1$
#336000
02
b1010011011001010111000101110101011001010110111001110100011010010110000101101100 1
b1010110 3
b101010000 4
#340000
0$
#345000
b1011000 !
b1011000 .
1$
#346000
b1010100011001010111001101110100001000000011100000111010001000000101000001000011001000000101001101110100011000010110110001101100001000000010100001110000011000110101111101100101011011100010000000111101001000000011000000101001 0
b1011000 3
b101011010 4
#350000
0)
0$
#355000
1$
#356000
b1010000010000110010000001110011011101000110000101101100011011000110010101100100 1
b101100100 4
#360000
0$
#365000
1$
#366000
b101101110 4
#370000
0$
#375000
1$
#376000
b101111000 4
#380000
0$
#385000
1$
#386000
b110000010 4
#390000
0$
#395000
1$
#396000
b110001100 4
#400000
1)
0$
#405000
b1011010 !
b1011010 .
1$
#406000
b1010011011001010111000101110101011001010110111001110100011010010110000101101100 1
b1011010 3
b110010110 4
#410000
0$
#415000
b1011100 !
b1011100 .
1$
#416000
b1011100 3
b110100000 4
#420000
0$
#425000
b1011110 !
b1011110 .
1$
#426000
b1010100011001010111001101110100001000000011100100111010001000000101001001100101011100110110010101110100 0
b1011110 3
b110101010 4
#430000
b0 !
b0 .
1*
0$
#435000
1$
#436000
b101001001100101011100110110010101110100001000000110000101110011011100110110010101110010011101000110010101100100 1
b0 3
b110110100 4
#440000
0*
0$
#445000
b10 !
b10 .
1$
#446000
b1110011011001010111010000100000011101100110010101110010011010010110011001101001011000110110000101110100011010010110111101101110 1
b10 3
b110111110 4
#450000
0$
#455000
b100 !
b100 .
1$
#456000
b1110100011010010110000101101100001000000110000101100110011101000110010101110010001000000111001001100101011100110110010101110100 1
b100 3
b111001000 4
#460000
0$
#465000
b110 !
b110 .
1$
#466000
b110 3
b111010010 4
#470000
0$
#475000
b1000 !
b1000 .
1$
#476000
b11101000100000010100000111001001101001011011110111001001101001011101000111100100100000001010000100101001000001010011000101001000100000001111100010000001001010010000010100110000100000001111100010000001000010011100100110000101101110011000110110100000101001 0
b1000 3
b111011100 4
#480000
b1000000000 (
b1000000000 -
1'
b100 %
b100 ,
1&
b10 "
b10 +
1#
0$
#485000
b1000000000 !
b1000000000 .
1$
#486000
0'
0&
0#
12
b1110000011100100110100101101111011100100110100101110100011110010010000001100011011011110111001001110010011001010110001101110100 1
b1000000000 3
b111100110 4
#490000
0$
#495000
b1000000010 !
b1000000010 .
1$
#500000
0$
#505000
b1000000100 !
b1000000100 .
1$
#510000
0$
#515000
b1000000110 !
b1000000110 .
1$
#520000
0$
#525000
b1000001000 !
b1000001000 .
1$
#530000
0$
#535000
b1000001010 !
b1000001010 .
1$
