riscv-16/register_file.v
`timescale 1ns / 1ps
module register_file(
    input            clk,          // Clock
    // Write port
    input            RegWrite,     // Write enable
    input  [2:0]     A3,           // Destination register
    input  [15:0]    WD3,          // Data to write
    // Read port 1
    input  [2:0]     A1,           // Source register 1
    output [15:0]    RD1,          // Data read from A1
    // Read port 2
    input  [2:0]     A2,           // Source register 2
    output [15:0]    RD2           // Data read from A2
);

    reg [15:0] reg_array [7:0];    // 8 registers X0-X7
    integer i;

    // Initialize registers to 0 at simulation start
    initial begin
        for(i = 0; i < 8; i = i + 1)
            reg_array[i] = 16'd0;
    end

    // Synchronous write
    always @(posedge clk) begin
        if (RegWrite && A3 != 3'b000)  // X0 is always 0
            reg_array[A3] <= WD3;
    end

    // Combinational reads
    assign RD1 = (A1 == 3'b000) ? 16'd0 : reg_array[A1];
    assign RD2 = (A2 == 3'b000) ? 16'd0 : reg_array[A2];

endmodule

riscv-16/tb/register_file_tb.v
`timescale 1ns / 1ps

module register_file_tb;

    // Inputs
    reg clk;
    reg RegWrite;
    reg [2:0] A3;         // Destination register
    reg [15:0] WD3;       // Data to write
    reg [2:0] A1;         // Read port 1
    reg [2:0] A2;         // Read port 2

    // Outputs
    wire [15:0] RD1;
    wire [15:0] RD2;

    // Instantiate the register file
    register_file uut (
        .clk(clk),
        .RegWrite(RegWrite),
        .A3(A3),
        .WD3(WD3),
        .A1(A1),
        .RD1(RD1),
        .A2(A2),
        .RD2(RD2)
    );

    // Clock generation: 10ns period
    initial clk = 0;
    always #5 clk = ~clk;

    initial begin
        $dumpfile("./waveform/Register_file.vcd");
        $dumpvars(0, register_file_tb);
    end

    // Test sequence
    initial begin
        $display("-----------------------------------------------------------------------------------------------------");
        $display("| Test# | Operation                  | A3 | WD3   | RegWrite | A1 | A2 | Expected RD1 | Expected RD2 | Pass? |");
        $display("-----------------------------------------------------------------------------------------------------");

        // -------------------------
        // Test 1: Write X1 = 100
        // -------------------------
        A3 = 3'b001; WD3 = 16'd100; RegWrite = 1'b1;
        A1 = 3'b001; A2 = 3'b010;
        #10; // Wait for posedge clk
        $display("| %5d | %25s | %2b | %5d | %8b | %2b | %2b | %12d | %12d |  %s  |",
                 1, "Write X1", A3, WD3, RegWrite, A1, A2, RD1, RD2, 
                 (RD1==100 && RD2==0) ? "YES" : "NO");

        // -------------------------
        // Test 2: Write X2 = 200
        // -------------------------
        A3 = 3'b010; WD3 = 16'd200; RegWrite = 1'b1;
        A1 = 3'b001; A2 = 3'b010;
        #10;
        $display("| %5d | %25s | %2b | %5d | %8b | %2b | %2b | %12d | %12d |  %s  |",
                 2, "Write X2", A3, WD3, RegWrite, A1, A2, RD1, RD2,
                 (RD1==100 && RD2==200) ? "YES" : "NO");

        // -------------------------
        // Test 3: Attempt write X0 = 999
        // -------------------------
        A3 = 3'b000; WD3 = 16'd999; RegWrite = 1'b1;
        A1 = 3'b000; A2 = 3'b001;
        #10;
        $display("| %5d | %25s | %2b | %5d | %8b | %2b | %2b | %12d | %12d |  %s  |",
                 3, "Write X0", A3, WD3, RegWrite, A1, A2, RD1, RD2,
                 (RD1==0 && RD2==100) ? "YES" : "NO");

        // -------------------------
        // Test 4: RegWrite=0, write ignored
        // -------------------------
        A3 = 3'b011; WD3 = 16'd300; RegWrite = 1'b0;
        A1 = 3'b011; A2 = 3'b010;
        #10;
        $display("| %5d | %25s | %2b | %5d | %8b | %2b | %2b | %12d | %12d |  %s  |",
                 4, "No write", A3, WD3, RegWrite, A1, A2, RD1, RD2,
                 (RD1==0 && RD2==200) ? "YES" : "NO");

        // -------------------------
        // Test 5: Overwrite X1 = 111
        // -------------------------
        A3 = 3'b001; WD3 = 16'd111; RegWrite = 1'b1;
        A1 = 3'b001; A2 = 3'b010;
        #10;
        $display("| %5d | %25s | %2b | %5d | %8b | %2b | %2b | %12d | %12d |  %s  |",
                 5, "Overwrite X1", A3, WD3, RegWrite, A1, A2, RD1, RD2,
                 (RD1==111 && RD2==200) ? "YES" : "NO");

        // -------------------------
        // Test 6: Read X0 always 0
        // -------------------------
        A1 = 3'b000; A2 = 3'b000; RegWrite = 1'b0;
        #10;
        $display("| %5d | %25s | %2s | %5s | %8b | %2b | %2b | %12d | %12d |  %s  |",
                 6, "Read X0", "-", "-", RegWrite, A1, A2, RD1, RD2,
                 (RD1==0 && RD2==0) ? "YES" : "NO");

        // -------------------------
        // Test 7: Simultaneous read/write to X2
        // Write X2 = 555 while reading X2 and X1
        // -------------------------
        A3 = 3'b010; WD3 = 16'd555; RegWrite = 1'b1;
        A1 = 3'b010;  // reading same register being written
        A2 = 3'b001;  // reading another register
        #1; // short delay within same cycle
        $display("| %5d | %25s | %2b | %5d | %8b | %2b | %2b | %12d | %12d |  %s  |",
                 7, "Simultaneous R/W", A3, WD3, RegWrite, A1, A2, RD1, RD2,
                 // Synchronous write: RD1 should still show old value (200), RD2 = X1 (111)
                 (RD1==200 && RD2==111) ? "YES" : "NO");
        #9; // wait for clock to apply write

        // -------------------------
        // Test 8: Read after simultaneous write
        // -------------------------
        A1 = 3'b010; A2 = 3'b001; RegWrite = 1'b0;
        #10;
        $display("| %5d | %25s | %2s | %5s | %8b | %2b | %2b | %12d | %12d |  %s  |",
                 8, "Read X2 after write", "-", "-", RegWrite, A1, A2, RD1, RD2,
                 (RD1==555 && RD2==111) ? "YES" : "NO");

        $display("-----------------------------------------------------------------------------------------------------");
        $display("Register File Test Bench Completed.");
        $finish;
    end

endmodule

riscv-16/tb/waveform/Register_file.vcd
$date
	Sat Oct 18 16:39:58 2025
$end
$version
	Icarus Verilog
$end
$timescale
	1ps
$end
$scope module register_file_tb $end
$var wire 16 ! RD2 [15:0] $end
$var wire 16 " RD1 [15:0] $end
$var reg 3 # A1 [2:0] $end
$var reg 3 $ A2 [2:0] $end
$var reg 3 % A3 [2:0] $end
$var reg 1 & RegWrite $end
$var reg 16 ' WD3 [15:0] $end
$var reg 1 ( clk $end
$scope module uut $end
$var wire 3 ) A1 [2:0] $end
$var wire 3 * A2 [2:0] $end
$var wire 3 + A3 [2:0] $end
$var wire 1 & RegWrite $end
$var wire 16 , WD3 [15:0] $end
$var wire 1 ( clk $end
$var wire 16 - RD2 [15:0] $end
$var wire 16 . RD1 [15:0] $end
$var integer 32 / i [31:0] $end
$upscope $end
$upscope $end
$enddefinitions $end
$comment Show the parameter values. $end
$dumpall
$end
#0
$dumpvars
b1000 /
b0 .
b0 -
b1100100 ,
b1 +
b10 *
b1 )
0(
b1100100 '
1&
b1 %
b10 $
b1 #
b0 "
b0 !
$end
#5000
b1100100 "
b1100100 .
1(
#10000
0(
b11001000 '
b11001000 ,
b10 %
b10 +
#15000
b11001000 !
b11001000 -
1(
#20000
b1100100 !
b1100100 -
b0 "
b0 .
0(
b1 $
b1 *
b0 #
b0 )
b1111100111 '
b1111100111 ,
b0 %
b0 +
#25000
1(
#30000
b11001000 !
b11001000 -
0(
b10 $
b10 *
b11 #
b11 )
0&
b100101100 '
b100101100 ,
b11 %
b11 +
#35000
1(
#40000
b1100100 "
b1100100 .
0(
b1 #
b1 )
1&
b1101111 '
b1101111 ,
b1 %
b1 +
#45000
b1101111 "
b1101111 .
1(
#50000
b0 !
b0 -
b0 "
b0 .
0(
0&
b0 $
b0 *
b0 #
b0 )
#55000
1(
#60000
b1101111 !
b1101111 -
b11001000 "
b11001000 .
0(
b1 $
b1 *
b10 #
b10 )
1&
b1000101011 '
b1000101011 ,
b10 %
b10 +
#65000
b1000101011 "
b1000101011 .
1(
#70000
0(
0&
