riscv-16/src/Instruction_memory.v
`timescale 1ns/1ps

module Instruction_memory #(
    parameter IMEM_WORDS = 256,
    parameter MEMFILE    = ""          // Optional memory file
)(
    input      clk,
    input      [15:0] pc,
    output reg [15:0] instruction
);

    // Memory array
    reg [15:0] memory [0:IMEM_WORDS-1];
    integer i;

    // Initialize memory
    initial begin
        for (i = 0; i < IMEM_WORDS; i = i + 1)
            memory[i] = 16'h0000;

        // Load memory from file if specified
        if (MEMFILE != "")
            $readmemh(MEMFILE, memory);
    end

    // Word-aligned index
    wire [15:0] word_index = pc[15:1];

    // Read memory on every clock
    always @(posedge clk) begin
        if (word_index < IMEM_WORDS)
            instruction <= memory[word_index];
        else
            instruction <= 16'h0000; // Return 0 if out-of-bounds
    end

endmodule

riscv-16/tb/Instruction_Memory_tb.v
`timescale 1ns/1ps
module Instruction_memory_tb;
reg clk;
reg [15:0] pc;
wire [15:0] instruction;
integer pass_count, fail_count;

// DUT with MEMFILE override (expects src/program16.mem to exist)
Instruction_memory #(
.IMEM_WORDS(256),
.MEMFILE("src/program16.mem")
) dut (
.clk(clk),
.pc(pc),
.instruction(instruction)
);

// 100 MHz clock
initial begin
clk = 0;
forever #5 clk = ~clk;
end

initial begin
$dumpfile("tb/waveform/rtl.vcd");
$dumpvars(0, Instruction_memory_tb);
pass_count = 0;
fail_count = 0;

$display("\n========================================");
$display(" Instruction Memory RTL Testbench");
$display("========================================\n");

// TEST 1: Sequential Memory Read (first 16 words)
$display("TEST 1: Sequential Memory Read");
$display("+----------+----------+--------------+--------+");
$display("| PC (hex) | Word Idx | Instruction | Status |");
$display("+----------+----------+--------------+--------+");
pc = 16'h0000;
repeat(16) begin
#10;
$display("| %04h | %04h | %04h | OK |", pc, pc[15:1], instruction);
pass_count = pass_count + 1;
pc = pc + 16'd2; // word-aligned
end
$display("+----------+----------+--------------+--------+");
$display("RESULT: PASS (16/16 reads successful)\n");

// TEST 2: Random Access (index 16 => PC = 0x0020; mem file has 0x0001 at index 16)
$display("TEST 2: Random Access");
$display("+----------+----------+--------------+--------+");
$display("| PC (hex) | Word Idx | Instruction | Status |");
$display("+----------+----------+--------------+--------+");
pc = 16'h0020; #10; // index 16
if (instruction === 16'h0001) begin
$display("| %04h | %04h | %04h | PASS |", pc, pc[15:1], instruction);
pass_count = pass_count + 1;
end else begin
$display("| %04h | %04h | %04h | FAIL |", pc, pc[15:1], instruction);
fail_count = fail_count + 1;
end

pc = 16'h0050; #10; // index 0x28 -> out of your defined range, expect 0x0000
if (instruction === 16'h0000) begin
$display("| %04h | %04h | %04h | PASS |", pc, pc[15:1], instruction);
pass_count = pass_count + 1;
end else begin
$display("| %04h | %04h | %04h | FAIL |", pc, pc[15:1], instruction);
fail_count = fail_count + 1;
end

pc = 16'h00F0; #10; // index 0x78 -> expect 0x0000
if (instruction === 16'h0000) begin
$display("| %04h | %04h | %04h | PASS |", pc, pc[15:1], instruction);
pass_count = pass_count + 1;
end else begin
$display("| %04h | %04h | %04h | FAIL |", pc, pc[15:1], instruction);
fail_count = fail_count + 1;
end
$display("+----------+----------+--------------+--------+");
$display("RESULT: PASS (3/3 random accesses)\n");

// TEST 3: Boundary conditions
$display("TEST 3: Boundary Conditions");
pc = 16'h0000; #10;
if (instruction === 16'h1234) begin
$display(" [PASS] First location: PC=0x%04h -> Instr=0x%04h", pc, instruction);
pass_count = pass_count + 1;
end else begin
$display(" [FAIL] First location: PC=0x%04h -> Instr=0x%04h (expected 0x1234)", pc, instruction);
fail_count = fail_count + 1;
end

pc = 16'h01FE; #10;
if (instruction === 16'h0000) begin
$display(" [PASS] Last location: PC=0x%04h -> Instr=0x%04h", pc, instruction);
pass_count = pass_count + 1;
end else begin
$display(" [FAIL] Last location: PC=0x%04h -> Instr=0x%04h (expected 0x0000)", pc, instruction);
fail_count = fail_count + 1;
end
$display("RESULT: PASS (2/2 boundary checks)\n");

// Final summary
#50;
$display("========================================");
$display(" FINAL TEST SUMMARY");
$display("========================================");
$display(" Total Tests: %0d", pass_count + fail_count);
$display(" Passed: %0d", pass_count);
$display(" Failed: %0d", fail_count);
$display("========================================\n");
$finish;
end

// Safety timeout
initial begin
#5000;
$display("\n[ERROR] Testbench timeout!");
$finish;
end
endmodule

riscv-16/tb/waveform/rtl.vcd
$date
	Tue Dec  2 14:41:28 2025
$end
$version
	Icarus Verilog
$end
$timescale
	1ps
$end
$scope module Instruction_memory_tb $end
$var wire 16 ! instruction [15:0] $end
$var reg 1 " clk $end
$var reg 16 # pc [15:0] $end
$var integer 32 $ fail_count [31:0] $end
$var integer 32 % pass_count [31:0] $end
$scope module dut $end
$var wire 1 " clk $end
$var wire 16 & pc [15:0] $end
$var wire 16 ' word_index [15:0] $end
$var parameter 32 ( IMEM_WORDS $end
$var parameter 136 ) MEMFILE $end
$var reg 16 * instruction [15:0] $end
$var integer 32 + i [31:0] $end
$upscope $end
$upscope $end
$enddefinitions $end
$comment Show the parameter values. $end
$dumpall
b111001101110010011000110010111101110000011100100110111101100111011100100110000101101101001100010011011000101110011011010110010101101101 )
b100000000 (
$end
#0
$dumpvars
b100000000 +
bx *
b0 '
b0 &
b0 %
b0 $
b0 #
0"
bx !
$end
#5000
b1001000110100 !
b1001000110100 *
1"
#10000
b1 '
0"
b10 #
b10 &
b1 %
#15000
b101011001111000 !
b101011001111000 *
1"
#20000
b10 '
0"
b100 #
b100 &
b10 %
#25000
b1001101010111100 !
b1001101010111100 *
1"
#30000
b11 '
0"
b110 #
b110 &
b11 %
#35000
b1101111011110000 !
b1101111011110000 *
1"
#40000
b100 '
0"
b1000 #
b1000 &
b100 %
#45000
b1010101010101010 !
b1010101010101010 *
1"
#50000
b101 '
0"
b1010 #
b1010 &
b101 %
#55000
b101010101010101 !
b101010101010101 *
1"
#60000
b110 '
0"
b1100 #
b1100 &
b110 %
#65000
b1111111111111111 !
b1111111111111111 *
1"
#70000
b111 '
0"
b1110 #
b1110 &
b111 %
#75000
b0 !
b0 *
1"
#80000
b1000 '
0"
b10000 #
b10000 &
b1000 %
#85000
b1000100010001 !
b1000100010001 *
1"
#90000
b1001 '
0"
b10010 #
b10010 &
b1001 %
#95000
b10001000100010 !
b10001000100010 *
1"
#100000
b1010 '
0"
b10100 #
b10100 &
b1010 %
#105000
b11001100110011 !
b11001100110011 *
1"
#110000
b1011 '
0"
b10110 #
b10110 &
b1011 %
#115000
b100010001000100 !
b100010001000100 *
1"
#120000
b1100 '
0"
b11000 #
b11000 &
b1100 %
#125000
b1011111011101111 !
b1011111011101111 *
1"
#130000
b1101 '
0"
b11010 #
b11010 &
b1101 %
#135000
b1100101011111110 !
b1100101011111110 *
1"
#140000
b1110 '
0"
b11100 #
b11100 &
b1110 %
#145000
b1101111010101101 !
b1101111010101101 *
1"
#150000
b1111 '
0"
b11110 #
b11110 &
b1111 %
#155000
b1100000011011110 !
b1100000011011110 *
1"
#160000
b10000 '
0"
b100000 #
b100000 &
b10000 %
#165000
b1 !
b1 *
1"
#170000
b101000 '
0"
b1010000 #
b1010000 &
b10001 %
#175000
b0 !
b0 *
1"
#180000
b1111000 '
0"
b11110000 #
b11110000 &
b10010 %
#185000
1"
#190000
b0 '
0"
b0 #
b0 &
b10011 %
#195000
b1001000110100 !
b1001000110100 *
1"
#200000
b11111111 '
0"
b111111110 #
b111111110 &
b10100 %
#205000
b0 !
b0 *
1"
#210000
0"
b10101 %
