riscv-16/src/Sign_Extender.v
`timescale 1ns / 1ps
module Sign_Extender(
    input  wire [15:0] instr,
    input  wire [2:0]  ImmSrc,   
    output reg  [15:0] ImmExt
);

always @(*) begin
    case (ImmSrc)
        3'b000: ImmExt = 16'b0;                                         // R-type: no immediate
        3'b001: ImmExt = {{13{instr[15]}}, instr[15:13]};                // I-type (ALU immediate)
        3'b010: ImmExt = {{9{instr[15]}}, instr[15:9]};                  // S-type (stores)
        3'b011: ImmExt = {{9{instr[15]}}, {instr[15:13], instr[12:9]}} << 1; // B-type (branches)
        3'b100: ImmExt = {instr[15:3], 3'b000};                          // U-type (upper bits)
        3'b101: ImmExt = {instr[15:6], 6'b000000};                       // J-type (jump and link)
        default: ImmExt = 16'b0;                                         // fallback
    endcase
end

endmodule

riscv-16/tb/Sign_Extender_tb.v
`timescale 1ns / 1ps
module Sign_Extender_tb;

    reg  [15:0] instr;
    reg  [2:0]  ImmSrc;    
    wire [15:0] ImmExt;

    Sign_Extender uut (
        .instr(instr),
        .ImmSrc(ImmSrc),
        .ImmExt(ImmExt)
    );

    // For waveform generation
    initial begin
        $dumpfile("./tb/waveform/Sign_Extender.vcd");
        $dumpvars(0, Sign_Extender_tb);
    end

    reg [15:0] expected;
    reg [8*8-1:0] instr_type; 

    initial begin
        
        $display("Instr               ImmSrc   Type      ImmExt               Expected             Pass");
        $display("-------------------------------------------------------------------------------------------");

        
// ---------------------- R-TYPE EDGE CASES ----------------------

        // All zeros 
        instr = 16'b0000000000000000; ImmSrc = 3'b000; instr_type = "R-TYPE"; expected = 16'b0; #10;
        $display("%-18b  %-7b  %-8s  %-18b  %-18b  %b", instr, ImmSrc, instr_type, ImmExt, expected, (ImmExt==expected));

        // All ones
        instr = 16'b1111111111111111; ImmSrc = 3'b000; instr_type = "R-TYPE"; expected = 16'b0; #10;
        $display("%-18b  %-7b  %-8s  %-18b  %-18b  %b", instr, ImmSrc, instr_type, ImmExt, expected, (ImmExt==expected));

        // Alternating bits 1010...
        instr = 16'b1010101010101010; ImmSrc = 3'b000; instr_type = "R-TYPE"; expected = 16'b0; #10;
        $display("%-18b  %-7b  %-8s  %-18b  %-18b  %b", instr, ImmSrc, instr_type, ImmExt, expected, (ImmExt==expected));

        // Alternating bits 0101...
        instr = 16'b0101010101010101; ImmSrc = 3'b000; instr_type = "R-TYPE"; expected = 16'b0; #10;
        $display("%-18b  %-7b  %-8s  %-18b  %-18b  %b", instr, ImmSrc, instr_type, ImmExt, expected, (ImmExt==expected));

        // Max positive 15-bit number in lower bits - Sign Extension check
        instr = 16'b0000111111111111; ImmSrc = 3'b000; instr_type = "R-TYPE"; expected = 16'b0; #10;
        $display("%-18b  %-7b  %-8s  %-18b  %-18b  %b", instr, ImmSrc, instr_type, ImmExt, expected, (ImmExt==expected));

        // Max negative 16-bit number
        instr = 16'b1000000000000000; ImmSrc = 3'b000; instr_type = "R-TYPE"; expected = 16'b0; #10;
        $display("%-18b  %-7b  %-8s  %-18b  %-18b  %b", instr, ImmSrc, instr_type, ImmExt, expected, (ImmExt==expected));


                // ---------------------- I-TYPE EDGE CASES ----------------------
        ImmSrc = 3'b001; instr_type = "I-TYPE";

        // Positive immediates
        instr = 16'b0000000000000000; expected = 16'b0000000000000000; #10;
        $display("%-18b  %-7b  %-8s  %-18b  %-18b  %b", instr, ImmSrc, instr_type, ImmExt, expected, (ImmExt==expected));

        instr = 16'b0010000000000000; expected = 16'b0000000000000001; #10;
        $display("%-18b  %-7b  %-8s  %-18b  %-18b  %b", instr, ImmSrc, instr_type, ImmExt, expected, (ImmExt==expected));

        instr = 16'b0100000000000000; expected = 16'b0000000000000010; #10;
        $display("%-18b  %-7b  %-8s  %-18b  %-18b  %b", instr, ImmSrc, instr_type, ImmExt, expected, (ImmExt==expected));

        instr = 16'b0110000000000000; expected = 16'b0000000000000011; #10;
        $display("%-18b  %-7b  %-8s  %-18b  %-18b  %b", instr, ImmSrc, instr_type, ImmExt, expected, (ImmExt==expected));

        // Negative immediates
        instr = 16'b1000000000000000; expected = 16'b1111111111111100; #10; // -4
        $display("%-18b  %-7b  %-8s  %-18b  %-18b  %b", instr, ImmSrc, instr_type, ImmExt, expected, (ImmExt==expected));

        instr = 16'b1010000000000000; expected = 16'b1111111111111101; #10; // -3
        $display("%-18b  %-7b  %-8s  %-18b  %-18b  %b", instr, ImmSrc, instr_type, ImmExt, expected, (ImmExt==expected));

        instr = 16'b1100000000000000; expected = 16'b1111111111111110; #10; // -2
        $display("%-18b  %-7b  %-8s  %-18b  %-18b  %b", instr, ImmSrc, instr_type, ImmExt, expected, (ImmExt==expected));

        instr = 16'b1110000000000000; expected = 16'b1111111111111111; #10; // -1
        $display("%-18b  %-7b  %-8s  %-18b  %-18b  %b", instr, ImmSrc, instr_type, ImmExt, expected, (ImmExt==expected));


        
        // ----------------------  S-TYPE (positive and negative edge cases) ----------------------
        // Case 1: largest positive number
        instr = 16'b0111111000000000; ImmSrc = 3'b010; instr_type = "S-TYPE"; expected = 16'b0000000000111111; #10;
        $display("%-18b  %-7b  %-8s  %-18b  %-18b  %b", instr, ImmSrc, instr_type, ImmExt, expected, (ImmExt==expected));

        // Case 2: largest negative number
        instr = 16'b1000000000000000; ImmSrc = 3'b010; instr_type = "S-TYPE"; expected = 16'b1111111111000000; #10;
        $display("%-18b  %-7b  %-8s  %-18b  %-18b  %b", instr, ImmSrc, instr_type, ImmExt, expected, (ImmExt==expected));

        // Case 3: smallest positive number
        instr = 16'b0000001000000000; ImmSrc = 3'b010; instr_type = "S-TYPE"; expected = 16'b0000000000000001; #10;
        $display("%-18b  %-7b  %-8s  %-18b  %-18b  %b", instr, ImmSrc, instr_type, ImmExt, expected, (ImmExt==expected));

        // Case 4: small negative number
        instr = 16'b1000001000000000; ImmSrc = 3'b010; instr_type = "S-TYPE"; expected = 16'b1111111111000001; #10;
        $display("%-18b  %-7b  %-8s  %-18b  %-18b  %b", instr, ImmSrc, instr_type, ImmExt, expected, (ImmExt==expected));

        // Case 5: typical middle value
        instr = 16'b0010101000000000; ImmSrc = 3'b010; instr_type = "S-TYPE"; expected = 16'b0000000000010101; #10;
        $display("%-18b  %-7b  %-8s  %-18b  %-18b  %b", instr, ImmSrc, instr_type, ImmExt, expected, (ImmExt==expected));


        
        // ----------------------  B-TYPE (positive and negative / edge cases) ----------------------
        instr = 16'b0111111000000000; ImmSrc = 3'b011; instr_type = "B-TYPE"; expected = 16'b0000000001111110; #10;
        $display("%-18b  %-7b  %-8s  %-18b  %-18b  %b", instr, ImmSrc, instr_type, ImmExt, expected, (ImmExt==expected));

        instr = 16'b0000001000000000; ImmSrc = 3'b011; instr_type = "B-TYPE"; expected = 16'b0000000000000010; #10;
        $display("%-18b  %-7b  %-8s  %-18b  %-18b  %b", instr, ImmSrc, instr_type, ImmExt, expected, (ImmExt==expected));


        instr = 16'b0010101000000000; ImmSrc = 3'b011; instr_type = "B-TYPE"; expected = 16'b0000000000101010; #10;
        $display("%-18b  %-7b  %-8s  %-18b  %-18b  %b", instr, ImmSrc, instr_type, ImmExt, expected, (ImmExt==expected));

        instr = 16'b1000000000000000; ImmSrc = 3'b011; instr_type = "B-TYPE"; expected = 16'b1111111110000000; #10;
        $display("%-18b  %-7b  %-8s  %-18b  %-18b  %b", instr, ImmSrc, instr_type, ImmExt, expected, (ImmExt==expected));

        instr = 16'b1000001000000000; ImmSrc = 3'b011; instr_type = "B-TYPE"; expected = 16'b1111111110000010; #10;
        $display("%-18b  %-7b  %-8s  %-18b  %-18b  %b", instr, ImmSrc, instr_type, ImmExt, expected, (ImmExt==expected));

        instr = 16'b1010101000000000; ImmSrc = 3'b011; instr_type = "B-TYPE"; expected = 16'b1111111110101010; #10;
        $display("%-18b  %-7b  %-8s  %-18b  %-18b  %b", instr, ImmSrc, instr_type, ImmExt, expected, (ImmExt==expected));


                
        // ----------------------  U-TYPE (positive / upper bits small) ----------------------
        instr = 16'b0000000000000000; ImmSrc = 3'b100; instr_type = "U-TYPE"; expected = 16'b0000000000000000; #10;
        $display("%-18b  %-7b  %-8s  %-18b  %-18b  %b", instr, ImmSrc, instr_type, ImmExt, expected, (ImmExt==expected));

        instr = 16'b0000000011111000; ImmSrc = 3'b100; instr_type = "U-TYPE"; expected = 16'b0000000011111000; #10;
        $display("%-18b  %-7b  %-8s  %-18b  %-18b  %b", instr, ImmSrc, instr_type, ImmExt, expected, (ImmExt==expected));

        // ----------------------  U-TYPE (positive / upper bits max) ----------------------
        instr = 16'b0111111111111000; ImmSrc = 3'b100; instr_type = "U-TYPE"; expected = 16'b0111111111111000; #10;
        $display("%-18b  %-7b  %-8s  %-18b  %-18b  %b", instr, ImmSrc, instr_type, ImmExt, expected, (ImmExt==expected));

        // ----------------------  U-TYPE (negative / sign bit set) ----------------------
        instr = 16'b1000000000000000; ImmSrc = 3'b100; instr_type = "U-TYPE"; expected = 16'b1000000000000000; #10;
        $display("%-18b  %-7b  %-8s  %-18b  %-18b  %b", instr, ImmSrc, instr_type, ImmExt, expected, (ImmExt==expected));

        instr = 16'b1111111111111000; ImmSrc = 3'b100; instr_type = "U-TYPE"; expected = 16'b1111111111111000; #10;
        $display("%-18b  %-7b  %-8s  %-18b  %-18b  %b", instr, ImmSrc, instr_type, ImmExt, expected, (ImmExt==expected));


        
        //----------------------  J-TYPE (positive)  ----------------------
        instr = 16'b0001111000010000; ImmSrc = 3'b101; instr_type = "J-TYPE"; expected = 16'b0001111000000000; #10;
        $display("%-18b  %-7b  %-8s  %-18b  %-18b  %b", instr, ImmSrc, instr_type, ImmExt, expected, (ImmExt==expected));

        // ---------------------- J-TYPE (negative). ----------------------
        instr = 16'b1001111000010000; ImmSrc = 3'b101; instr_type = "J-TYPE"; expected = 16'b1001111000000000; #10;
        $display("%-18b  %-7b  %-8s  %-18b  %-18b  %b", instr, ImmSrc, instr_type, ImmExt, expected, (ImmExt==expected));

        
        //  ---------------------- INVALID / default  ----------------------
        instr = 16'b1111111111111111; ImmSrc = 3'b110; instr_type = "X"; expected = 16'b0; #10;
        $display("%-18b  %-7b  %-8s  %-18b  %-18b  %b", instr, ImmSrc, instr_type, ImmExt, expected, (ImmExt==expected));

        $finish;
    end

endmodule

riscv-16/tb/waveform/Sign_Extender.vcd
$date
	Fri Jan 30 09:12:49 2026
$end
$version
	Icarus Verilog
$end
$timescale
	1ps
$end
$scope module Sign_Extender_tb $end
$var wire 16 ! ImmExt [15:0] $end
$var reg 3 " ImmSrc [2:0] $end
$var reg 16 # expected [15:0] $end
$var reg 16 $ instr [15:0] $end
$var reg 64 % instr_type [63:0] $end
$scope module uut $end
$var wire 3 & ImmSrc [2:0] $end
$var wire 16 ' instr [15:0] $end
$var reg 16 ( ImmExt [15:0] $end
$upscope $end
$upscope $end
$enddefinitions $end
$comment Show the parameter values. $end
$dumpall
$end
#0
$dumpvars
b0 (
b0 '
b0 &
b10100100010110101010100010110010101000001000101 %
b0 $
b0 #
b0 "
b0 !
$end
#10000
b1111111111111111 $
b1111111111111111 '
#20000
b1010101010101010 $
b1010101010101010 '
#30000
b101010101010101 $
b101010101010101 '
#40000
b111111111111 $
b111111111111 '
#50000
b1000000000000000 $
b1000000000000000 '
#60000
b0 $
b0 '
b10010010010110101010100010110010101000001000101 %
b1 "
b1 &
#70000
b1 !
b1 (
b1 #
b10000000000000 $
b10000000000000 '
#80000
b10 !
b10 (
b10 #
b100000000000000 $
b100000000000000 '
#90000
b11 !
b11 (
b11 #
b110000000000000 $
b110000000000000 '
#100000
b1111111111111100 !
b1111111111111100 (
b1111111111111100 #
b1000000000000000 $
b1000000000000000 '
#110000
b1111111111111101 !
b1111111111111101 (
b1111111111111101 #
b1010000000000000 $
b1010000000000000 '
#120000
b1111111111111110 !
b1111111111111110 (
b1111111111111110 #
b1100000000000000 $
b1100000000000000 '
#130000
b1111111111111111 !
b1111111111111111 (
b1111111111111111 #
b1110000000000000 $
b1110000000000000 '
#140000
b111111 !
b111111 (
b111111 #
b10100110010110101010100010110010101000001000101 %
b10 "
b10 &
b111111000000000 $
b111111000000000 '
#150000
b1111111111000000 !
b1111111111000000 (
b1111111111000000 #
b1000000000000000 $
b1000000000000000 '
#160000
b1 !
b1 (
b1 #
b1000000000 $
b1000000000 '
#170000
b1111111111000001 !
b1111111111000001 (
b1111111111000001 #
b1000001000000000 $
b1000001000000000 '
#180000
b10101 !
b10101 (
b10101 #
b10101000000000 $
b10101000000000 '
#190000
b1111110 !
b1111110 (
b1111110 #
b10000100010110101010100010110010101000001000101 %
b11 "
b11 &
b111111000000000 $
b111111000000000 '
#200000
b10 !
b10 (
b10 #
b1000000000 $
b1000000000 '
#210000
b101010 !
b101010 (
b101010 #
b10101000000000 $
b10101000000000 '
#220000
b1111111110000000 !
b1111111110000000 (
b1111111110000000 #
b1000000000000000 $
b1000000000000000 '
#230000
b1111111110000010 !
b1111111110000010 (
b1111111110000010 #
b1000001000000000 $
b1000001000000000 '
#240000
b1111111110101010 !
b1111111110101010 (
b1111111110101010 #
b1010101000000000 $
b1010101000000000 '
#250000
b0 !
b0 (
b0 #
b10101010010110101010100010110010101000001000101 %
b100 "
b100 &
b0 $
b0 '
#260000
b11111000 !
b11111000 (
b11111000 #
b11111000 $
b11111000 '
#270000
b111111111111000 !
b111111111111000 (
b111111111111000 #
b111111111111000 $
b111111111111000 '
#280000
b1000000000000000 !
b1000000000000000 (
b1000000000000000 #
b1000000000000000 $
b1000000000000000 '
#290000
b1111111111111000 !
b1111111111111000 (
b1111111111111000 #
b1111111111111000 $
b1111111111111000 '
#300000
b1111000000000 !
b1111000000000 (
b1111000000000 #
b10010100010110101010100010110010101000001000101 %
b101 "
b101 &
b1111000010000 $
b1111000010000 '
#310000
b1001111000000000 !
b1001111000000000 (
b1001111000000000 #
b1001111000010000 $
b1001111000010000 '
#320000
b0 !
b0 (
b0 #
b1011000 %
b110 "
b110 &
b1111111111111111 $
b1111111111111111 '
