riscv-16/src/Sign_Extender.v
`timescale 1ns / 1ps
module Sign_Extender(
    input  wire [15:0] instr,
    input  wire [1:0] ImmSrc,   // select immediate type
    output reg  [15:0] ImmExt
);

always @(*) begin
    case (ImmSrc)
        2'b00: ImmExt = {{13{instr[15]}}, instr[15:13]};                // I-type
        2'b01: ImmExt = {{9{instr[15]}}, {instr[15:13], instr[12:9]}}; // B-type
        2'b10: ImmExt = {instr[15:6], 6'b000000};                       // J-type
        2'b11: ImmExt = {{9{instr[15]}}, instr[15:9]};                  // S-type
        default: ImmExt = 16'b0;                                        // fallback
    endcase
end

endmodule

riscv-16/tb/Sign_Extender_tb.v
`timescale 1ns / 1ps
module Sign_Extender_tb;

    reg  [15:0] instr;
    reg  [1:0]  ImmSrc;
    wire [15:0] ImmExt;

    Sign_Extender uut (
        .instr(instr),
        .ImmSrc(ImmSrc),
        .ImmExt(ImmExt)
    );

    // For waveform generation
    initial begin
        $dumpfile("./tb/waveform/Sign_Extender.vcd");
        $dumpvars(0, Sign_Extender_tb);
    end

    reg [15:0] expected;
    reg [8*1:0] instr_type; // instruction type as string

    initial begin
        // Table header with wider spacing
        $display("Instr               ImmSrc   Type    ImmExt               Expected             Pass");
        $display("-----------------------------------------------------------------------------------------");

        // R-TYPE
        instr = 16'b0000000000000000; ImmSrc = 2'b00; instr_type = "R"; expected = 16'b0000000000000000; #10;
        $display("%-18b  %-7b  %-5s  %-18b  %-18b  %b", instr, ImmSrc, instr_type, ImmExt, expected, (ImmExt==expected));

        // I-TYPE (positive)
        instr = 16'b0110000000000000; ImmSrc = 2'b00; instr_type = "I"; expected = {{13{1'b0}}, instr[15:13]}; #10;
        $display("%-18b  %-7b  %-5s  %-18b  %-18b  %b", instr, ImmSrc, instr_type, ImmExt, expected, (ImmExt==expected));

        // I-TYPE (negative)
        instr = 16'b1010000000000000; ImmSrc = 2'b00; instr_type = "I"; expected = {{13{1'b1}}, instr[15:13]}; #10;
        $display("%-18b  %-7b  %-5s  %-18b  %-18b  %b", instr, ImmSrc, instr_type, ImmExt, expected, (ImmExt==expected));

        // S-TYPE
        instr = 16'b0010101000000000; ImmSrc = 2'b11; instr_type = "S"; expected = {{9{1'b0}}, instr[15:9]}; #10;
        $display("%-18b  %-7b  %-5s  %-18b  %-18b  %b", instr, ImmSrc, instr_type, ImmExt, expected, (ImmExt==expected));

        instr = 16'b1010101000000000; ImmSrc = 2'b11; instr_type = "S"; expected = {{9{1'b1}}, instr[15:9]}; #10;
        $display("%-18b  %-7b  %-5s  %-18b  %-18b  %b", instr, ImmSrc, instr_type, ImmExt, expected, (ImmExt==expected));

        // B-TYPE
        instr = 16'b0010101000000000; ImmSrc = 2'b01; instr_type = "B"; expected = {{9{1'b0}}, {instr[15:13], instr[12:9]}}; #10;
        $display("%-18b  %-7b  %-5s  %-18b  %-18b  %b", instr, ImmSrc, instr_type, ImmExt, expected, (ImmExt==expected));

        instr = 16'b1010101000000000; ImmSrc = 2'b01; instr_type = "B"; expected = {{9{1'b1}}, {instr[15:13], instr[12:9]}}; #10;
        $display("%-18b  %-7b  %-5s  %-18b  %-18b  %b", instr, ImmSrc, instr_type, ImmExt, expected, (ImmExt==expected));

        // U-TYPE
        instr = 16'b0001100011110000; ImmSrc = 2'b10; instr_type = "U"; expected = {instr[15:6], 6'b000000}; #10;
        $display("%-18b  %-7b  %-5s  %-18b  %-18b  %b", instr, ImmSrc, instr_type, ImmExt, expected, (ImmExt==expected));

        instr = 16'b1001100011110000; ImmSrc = 2'b10; instr_type = "U"; expected = {instr[15:6], 6'b000000}; #10;
        $display("%-18b  %-7b  %-5s  %-18b  %-18b  %b", instr, ImmSrc, instr_type, ImmExt, expected, (ImmExt==expected));

        // J-TYPE
        instr = 16'b0001111000010000; ImmSrc = 2'b10; instr_type = "J"; expected = {instr[15:6], 6'b000000}; #10;
        $display("%-18b  %-7b  %-5s  %-18b  %-18b  %b", instr, ImmSrc, instr_type, ImmExt, expected, (ImmExt==expected));

        instr = 16'b1001111000010000; ImmSrc = 2'b10; instr_type = "J"; expected = {instr[15:6], 6'b000000}; #10;
        $display("%-18b  %-7b  %-5s  %-18b  %-18b  %b", instr, ImmSrc, instr_type, ImmExt, expected, (ImmExt==expected));

        // INVALID ImmSrc
        instr = 16'b1111111111111111; ImmSrc = 2'bxx; instr_type = "X"; expected = 16'b0; #10;
        $display("%-18b  %-7b  %-5s  %-18b  %-18b  %b", instr, ImmSrc, instr_type, ImmExt, expected, (ImmExt==expected));

        $finish;
    end

endmodule

riscv-16/tb/waveform/Sign_Extender.vcd
$date
	Thu Nov 13 16:25:12 2025
$end
$version
	Icarus Verilog
$end
$timescale
	1ps
$end
$scope module Sign_Extender_tb $end
$var wire 16 ! ImmExt [15:0] $end
$var reg 2 " ImmSrc [1:0] $end
$var reg 16 # expected [15:0] $end
$var reg 16 $ instr [15:0] $end
$var reg 9 % instr_type [8:0] $end
$scope module uut $end
$var wire 2 & ImmSrc [1:0] $end
$var wire 16 ' instr [15:0] $end
$var reg 16 ( ImmExt [15:0] $end
$upscope $end
$upscope $end
$enddefinitions $end
$comment Show the parameter values. $end
$dumpall
$end
#0
$dumpvars
b0 (
b0 '
b0 &
b1010010 %
b0 $
b0 #
b0 "
b0 !
$end
#10000
b11 !
b11 (
b11 #
b1001001 %
b110000000000000 $
b110000000000000 '
#20000
b1111111111111101 !
b1111111111111101 (
b1111111111111101 #
b1010000000000000 $
b1010000000000000 '
#30000
b10101 !
b10101 (
b10101 #
b1010011 %
b11 "
b11 &
b10101000000000 $
b10101000000000 '
#40000
b1111111111010101 !
b1111111111010101 (
b1111111111010101 #
b1010101000000000 $
b1010101000000000 '
#50000
b10101 !
b10101 (
b10101 #
b1000010 %
b1 "
b1 &
b10101000000000 $
b10101000000000 '
#60000
b1111111111010101 !
b1111111111010101 (
b1111111111010101 #
b1010101000000000 $
b1010101000000000 '
#70000
b1100011000000 !
b1100011000000 (
b1100011000000 #
b1010101 %
b10 "
b10 &
b1100011110000 $
b1100011110000 '
#80000
b1001100011000000 !
b1001100011000000 (
b1001100011000000 #
b1001100011110000 $
b1001100011110000 '
#90000
b1111000000000 !
b1111000000000 (
b1111000000000 #
b1001010 %
b1111000010000 $
b1111000010000 '
#100000
b1001111000000000 !
b1001111000000000 (
b1001111000000000 #
b1001111000010000 $
b1001111000010000 '
#110000
b0 !
b0 (
b0 #
b1011000 %
bx "
bx &
b1111111111111111 $
b1111111111111111 '
