riscv-16/Parameter.v
`ifndef PARAMETER_H_
`define PARAMETER_H_

`define col   16
`define row_d 8

`endif

riscv-16/Data_Memory.v
`include "Parameter.v"
// Verilog-2001 SRAM-like Data Memory (flip-flop implementation)
// Uses Parameter.v: `col = 16, `row_d = 8

module Data_Memory(
  input         clk,
  input  [15:0] mem_access_addr,  // byte address; word index uses [3:1]
  input  [15:0] mem_write_data,
  input         mem_write_en,
  input         mem_read,
  output [15:0] mem_read_data
);
  // Memory array: 8 words x 16 bits (from `row_d and `col)
  reg [`col-1:0] memory [0:`row_d-1];

  // Word-aligned index (drop bit0). With `row_d=8, index width = 3 bits.
  wire [2:0] addr = mem_access_addr[3:1];

  // Synchronous write
  always @(posedge clk) begin
    if (mem_write_en)
      memory[addr] <= mem_write_data;
  end

  // Combinational read with write-first semantics
  assign mem_read_data =
      mem_read
        ? (mem_write_en ? mem_write_data : memory[addr])
        : 16'h0000;

endmodule

riscv-16/ALU.v
module ALU (
    input  [15:0] SrcA,
    input  [15:0] SrcB,
    input  [3:0]  ALU_control,
    output reg [15:0] ALU_result,
    output           zero
);

always @(*) begin
    case (ALU_control)
        4'b0000: ALU_result = SrcA + SrcB;                 // ADD / ADDI / Load / Store / JALR
        4'b0001: ALU_result = SrcA - SrcB;                 // SUB
        4'b0010: ALU_result = SrcA ^ SrcB;                 // XOR / XORI
        4'b0011: ALU_result = SrcA | SrcB;                 // OR / ORI
        4'b0100: ALU_result = SrcA & SrcB;                 // AND / ANDI
        4'b0101: ALU_result = SrcA << SrcB[3:0];           // SLL
        4'b0110: ALU_result = SrcA >> SrcB[3:0];           // SRL
        4'b0111: ALU_result = $signed(SrcA) >>> SrcB[3:0]; // SRA
        4'b1000: ALU_result = SrcA + 16'd2;               // JAL (PC + 2)
        default: ALU_result = 16'h0000;
    endcase
end

assign zero = (ALU_result == 16'd0);

endmodule

riscv-16/src/ALUSrc_mux.v
`timescale 1ns/1ps

module ALUSrc_mux(
    input [15:0] RD2,       // Data from register file
    input [15:0] ImmExt,    // Sign-extended immediate
    input ALUSrc,           // Control signal from Control Unit
    output [15:0] SrcB   // Output to ALU
);

    assign SrcB = (ALUSrc) ? ImmExt : RD2;

endmodule

riscv-16/src/Sign_Extender.v
`timescale 1ns / 1ps
module Sign_Extender(
    input  wire [15:0] instr,
    input  wire [2:0]  ImmSrc,   
    output reg  [15:0] ImmExt
);

always @(*) begin
    case (ImmSrc)
        3'b000: ImmExt = 16'b0;                                         // R-type: no immediate
        3'b001: ImmExt = {{13{instr[15]}}, instr[15:13]};                // I-type (ALU immediate)
        3'b010: ImmExt = {{9{instr[15]}}, instr[15:9]};                  // S-type (stores)
        3'b011: ImmExt = {{9{instr[15]}}, {instr[15:13], instr[12:9]}} << 1; // B-type (branches)
        3'b100: ImmExt = {instr[15:6], 6'b000000};                          // U-type (upper bits)
        3'b101: ImmExt = {{6{instr[15]}}, instr[15:6]} << 1;             // J-type (jump and link)
        default: ImmExt = 16'b0;                                         // fallback
    endcase
end

endmodule

riscv-16/src/Register_file.v
`timescale 1ns / 1ps
module Register_file(
    input            clk,          // Clock
    // Write port
    input            RegWrite,     // Write enable
    input  [2:0]     A3,           // Destination register
    input  [15:0]    WD3,          // Data to write
    // Read port 1
    input  [2:0]     A1,           // Source register 1
    output [15:0]    RD1,          // Data read from A1
    // Read port 2
    input  [2:0]     A2,           // Source register 2
    output [15:0]    RD2,          // Data read from A2    

    // Debug: expose X1
    output [15:0]    dbg_x1,
    output [15:0]    dbg_x2,
    output [15:0]    dbg_x3
);
    reg [15:0] reg_array [7:0];    // 8 registers X0-X7
    integer i;

    // Initialize registers to 0 at simulation start
    initial begin
        for(i = 0; i < 8; i = i + 1)
            reg_array[i] = 16'd0;
    end

    // Synchronous write
    always @(posedge clk) begin
        if (RegWrite && A3 != 3'b000)  // X0 is always 0
            reg_array[A3] <= WD3;
    end

    // Combinational reads
    assign RD1 = (A1 == 3'b000) ? 16'd0 : reg_array[A1];
    assign RD2 = (A2 == 3'b000) ? 16'd0 : reg_array[A2];

    // Debug output
    assign dbg_x1 = reg_array[3'b001]; // X
    assign dbg_x2 = reg_array[3'b010]; // X2
    assign dbg_x3 = reg_array[3'b011]; // X3
endmodule

riscv-16/src/Control_unit.v
`timescale 1ns / 1ps

module Control_unit(
    input  [2:0] opcode,      // primary opcode
    input  [3:0] func,        // function field (R-type, I-type)
    input        zero,        // ALU zero flag (for branches)
    output reg        PCSrc,        // PC source select
    output reg        ResultSrc,    // result source select
    output reg        MemWrite,     // memory write enable
    output reg  [3:0] ALUControl,   // ALU operation select
    output reg        ALUSrc,       // ALU source select
    output reg  [2:0] ImmSrc,       // immediate type select
    output reg        RegWrite      // register file write enable
);

    always @(*) begin
        // Default values (NOP-safe)
        PCSrc      = 1'b0;
        ResultSrc  = 1'b0;
        MemWrite   = 1'b0;
        ALUControl = 4'b0000;
        ALUSrc     = 1'b0;
        ImmSrc     = 3'b000;
        RegWrite   = 1'b0;

        case (opcode)

            // ------------------------------------------------
            // R-type: opcode = 000
            // ------------------------------------------------
            3'b000: begin
                RegWrite   = 1'b1;
                ALUSrc     = 1'b0;
                ResultSrc  = 1'b0;
                ALUControl = func; // func directly controls ALU op
            end

            // ------------------------------------------------
            // I-type: opcode = 001
            // (addi/xori/ori/andi/jalr)
            // ------------------------------------------------
            3'b001: begin
                ALUSrc     = 1'b1;
                RegWrite   = 1'b1;
                ResultSrc  = 1'b0;
                ImmSrc     = 3'b001;

                // Decode func field
                case (func)
                    4'b0000: ALUControl = 4'b0000; // ADDI
                    4'b0001: ALUControl = 4'b0010; // XORI
                    4'b0010: ALUControl = 4'b0011; // ORI
                    4'b0011: ALUControl = 4'b0100; // ANDI
                    4'b1101: begin                  // JALR
                                ALUControl = 4'b0000; // ALU does addition (rs1 + imm)
                                ImmSrc     = 3'b001; // JALR immediate format
                                PCSrc      = 1'b1;
                            end
                    default: ALUControl = 4'b0000;
                endcase
            end

            // ------------------------------------------------
            // LW: opcode = 010
            // ------------------------------------------------
            3'b010: begin
                ALUSrc     = 1'b1;
                RegWrite   = 1'b1;
                ResultSrc  = 1'b1; // writeback from memory
                ALUControl = 4'b0000; // ADD base + offset
                ImmSrc     = 3'b001;
            end

            // ------------------------------------------------
            // SW: opcode = 011
            // ------------------------------------------------
            3'b011: begin
                ALUSrc     = 1'b1;
                MemWrite   = 1'b1;
                ALUControl = 4'b0000; // ADD base + offset
                ImmSrc     = 3'b001;
            end

            // ------------------------------------------------
            // Branches: opcode = 100
            // func = 000 (BEQ), 001 (BNE)
            // ------------------------------------------------
            3'b100: begin
                ALUSrc     = 1'b0;
                ALUControl = 4'b0001; // SUB for comparison
                ImmSrc     = 3'b011;
                RegWrite   = 1'b0;

                // Branch condition
                case (func[0])
                    1'b0: PCSrc = (zero) ? 1'b1 : 1'b0;  // BEQ
                    1'b1: PCSrc = (~zero) ? 1'b1 : 1'b0; // BNE
                endcase
            end

            // ------------------------------------------------
            // JAL: opcode = 101
            // ------------------------------------------------
            3'b101: begin
                PCSrc      = 1'b1;
                RegWrite   = 1'b1;
                ALUSrc     = 1'b1;
                ALUControl = 4'b0000; // Add PC + imm
                ImmSrc     = 3'b101;
                ResultSrc  = 1'b0;
            end

            // ------------------------------------------------
            // U-TYPE: opcode = 110  (LUI)
            // ------------------------------------------------
            3'b110: begin
                PCSrc      = 1'b0;        // No branch
                RegWrite   = 1'b1;        // Write to rd
                ALUSrc     = 1'b1;        // Use immediate
                ALUControl = 4'b0000;     // ADD (x0 + imm)
                ImmSrc     = 3'b100;       // Select U-type immediate
                ResultSrc  = 1'b0;        // Write ALU result
            end


            // ------------------------------------------------
            // Default (NOP)
            // ------------------------------------------------
            default: begin
                PCSrc      = 1'b0;
                ResultSrc  = 1'b0;
                MemWrite   = 1'b0;
                ALUControl = 4'b0000;
                ALUSrc     = 1'b0;
                ImmSrc     = 2'b00;
                RegWrite   = 1'b0;
            end
        endcase
    end
endmodule

riscv-16/src/Instruction_memory.v
`timescale 1ns/1ps

module Instruction_memory #(
    parameter IMEM_WORDS = 256,
    parameter MEMFILE    = ""          // Optional memory file
)(
    input      clk,
    input      [15:0] pc,
    output reg [15:0] instruction
);

    // Memory array
    reg [15:0] memory [0:IMEM_WORDS-1];
    integer i;

    // Initialize memory
    initial begin
        for (i = 0; i < IMEM_WORDS; i = i + 1)
            memory[i] = 16'h0000;

        // Load memory from file if specified
        if (MEMFILE != "")
            $readmemh(MEMFILE, memory);
    end

    // Word-aligned index
    wire [15:0] word_index = pc[15:1];

    // Read memory on every clock
    always @(posedge clk) begin
        if (word_index < IMEM_WORDS)
            instruction <= memory[word_index];
        else
            instruction <= 16'h0000; // Return 0 if out-of-bounds
    end

endmodule

riscv-16/PC_Counter.v
`timescale 1ns / 1ps

module pc_counter_16 (
    input              clk,
    input              reset,
    input              pc_en,           // enable (for stalls)

    // Branch control (B-type, opcode=011)
    input              branch_taken,
    input signed [6:0] branch_imm,     // signed halfword offset from B-type [2]

    // JAL (J-type, opcode=101)
    input              jal_taken,
    input signed [9:0] jal_imm,        // signed halfword offset from J-type [2]

    // JALR (I-type, func=1101)
    input              jalr_taken,
    input      [15:0]  jalr_target,    // rs1 + imm (byte address)

    output reg [15:0]  pc
);
    // Convert halfword offsets to byte addresses
    function [15:0] hw_to_bytes;
        input signed [15:0] imm_hw;
        begin
            hw_to_bytes = imm_hw << 1;
        end
    endfunction

    always @(posedge clk or posedge reset) begin
        if (reset) begin
            pc <= 16'h0000;
        end else if (pc_en) begin
            if (jalr_taken) begin
                // JALR: PC = rs1 + imm, align to 2-byte boundary [1]
                pc <= {jalr_target[15:1], 1'b0};
            end else if (jal_taken) begin
                // JAL: PC += imm (halfwords → bytes), rd = PC+2 in WB [1]
                pc <= pc + hw_to_bytes({{6{jal_imm[9]}}, jal_imm});
            end else if (branch_taken) begin
                // Branch: PC += imm (halfwords → bytes) [2]
                pc <= pc + hw_to_bytes({{9{branch_imm[6]}}, branch_imm});
            end else begin
                // Sequential: next 16-bit instruction
                pc <= pc + 16'd2;
            end
        end
    end
endmodule

riscv-16/src/top.v
`timescale 1ns / 1ps

module riscv16_top (
    input  wire       clk,
    input  wire       reset,

    // Debug outputs
    output wire [15:0] dbg_pc,
    output wire [15:0] dbg_instr,
    output wire [15:0] dbg_alu_result,
    output wire [15:0] dbg_x1,
    output wire [15:0] dbg_x2,
    output wire [15:0] dbg_x3
);

    /* =====================
       IF Stage
    ====================== */
    wire [15:0] PC, PC_next, PC_plus2, PC_target;
    wire [15:0] instruction;

    assign PC_plus2 = PC + 16'd2;

    // NOTE: pc_counter_16 from the report does not take PC_next as an input [1].
    // It computes next PC internally based on branch/jal/jalr signals.
    // For now we tie branch/jal/jalr inactive so it behaves like PC := PC+2.
    pc_counter_16 PC_REG (
        .clk(clk),
        .reset(reset),
        .pc_en(1'b1),

        .branch_taken(1'b0),
        .branch_imm(7'sd0),

        .jal_taken(1'b0),
        .jal_imm(10'sd0),

        .jalr_taken(1'b0),
        .jalr_target(16'h0000),

        .pc(PC)
    );

    Instruction_memory #(
        .IMEM_WORDS(256),
        .MEMFILE("src/program16.mem")
    ) IMEM (
        .clk(clk),
        .pc(PC),
        .instruction(instruction)
    );

    /* =====================
    Instruction Fields
    ===================== */

    wire [2:0] opcode = instruction[2:0];

    localparam OPC_R = 3'b000;
    localparam OPC_I = 3'b001;
    localparam OPC_S = 3'b010;
    localparam OPC_B = 3'b011;
    localparam OPC_U = 3'b110;
    localparam OPC_J = 3'b100;

    wire [3:0] func = instruction[6:3];

    /* =====================
    Raw Field Extraction
    ===================== */

    // ---------- R-Type ----------
    wire [2:0] rs1_r = instruction[15:13];
    wire [2:0] rs2_r = instruction[12:10];
    wire [2:0] rd_r  = instruction[9:7];

    // ---------- I-Type ----------
    wire [5:0] imm_i_raw = instruction[15:10];   // imm[2:0]
    wire [2:0] rs1_i     = instruction[9:7];
    wire [2:0] rd_i      = instruction[9:7];

    // ---------- S-Type ----------
    wire [6:0] imm_s_raw = instruction[15:9];    // imm[6:0]
    wire [2:0] rs1_s     = instruction[8:6];
    wire [2:0] rs2_s     = instruction[5:3];

    // ---------- B-Type ----------
    wire [2:0] imm_b_hi  = instruction[15:13];   // imm[6:4]
    wire [3:0] imm_b_lo  = instruction[12:9];    // imm[3:0]
    wire [2:0] rs1_b     = instruction[8:6];
    wire [2:0] rs2_b     = instruction[5:3];

    // ---------- U-Type ----------
    wire [9:0] imm_u_raw = instruction[15:6];    // imm[12:3]
    wire [2:0] rd_u      = instruction[5:3];

    // ---------- J-Type ----------
    wire [9:0] imm_j_raw = instruction[15:6];    // imm[15:6]
    wire [2:0] rd_j      = instruction[5:3];


    /* =====================
    Register Selection
    ===================== */

    wire [2:0] rs1 =
        (opcode == OPC_R) ? rs1_r :
        (opcode == OPC_I) ? rs1_i :
        (opcode == OPC_S) ? rs1_s :
        (opcode == OPC_B) ? rs1_b :
        3'b000;

    wire [2:0] rs2 =
        (opcode == OPC_R) ? rs2_r :
        (opcode == OPC_S) ? rs2_s :
        (opcode == OPC_B) ? rs2_b :
        3'b000;

    wire [2:0] rd =
        (opcode == OPC_R) ? rd_r :
        (opcode == OPC_I) ? rd_i :
        (opcode == OPC_U) ? rd_u :
        (opcode == OPC_J) ? rd_j :
        3'b000;


    /* =====================
    Immediate Construction
    ===================== */

    // Sign-extend immediates to 16 bits

    wire [15:0] imm_i = {{13{imm_i_raw[2]}}, imm_i_raw};              // 3-bit signed
    wire [15:0] imm_s = {{9{imm_s_raw[6]}}, imm_s_raw};               // 7-bit signed
    wire [15:0] imm_b = {{9{imm_b_hi[2]}}, imm_b_hi, imm_b_lo};       // 7-bit signed
    wire [15:0] imm_u = {imm_u_raw, 6'b000000};                       // upper immediate
    wire [15:0] imm_j = {{6{imm_j_raw[9]}}, imm_j_raw};               // 10-bit signed


    /* =====================
    Unified Immediate Output
    ===================== */

    wire [15:0] imm =
        (opcode == OPC_I) ? imm_i :
        (opcode == OPC_S) ? imm_s :
        (opcode == OPC_B) ? imm_b :
        (opcode == OPC_U) ? imm_u :
        (opcode == OPC_J) ? imm_j :
        16'h0000;


    /* =====================
       Control Unit
    ====================== */
    wire        PCSrc;
    wire        ResultSrc;
    wire        MemWrite;
    wire        ALUSrc;
    wire        RegWrite;
    wire [2:0]  ImmSrc;
    wire [3:0]  ALUControl;
    wire        zero;

    // Use the actual module name Control_Unit from the report [1]
    Control_unit CU (
        .opcode(opcode),
        .func(func),
        .zero(zero),
        .PCSrc(PCSrc),
        .ResultSrc(ResultSrc),
        .MemWrite(MemWrite),
        .ALUControl(ALUControl),
        .ALUSrc(ALUSrc),
        .ImmSrc(ImmSrc),
        .RegWrite(RegWrite)
    );

    /* =====================
       Register File
    ====================== */
    wire [15:0] RD1, RD2, WD3;
    wire [15:0] rf_dbg_x1;
    wire [15:0] rf_dbg_x2;
    wire [15:0] rf_dbg_x3;

    // Match your Register_file port names from the report [1]
    Register_file RF (
        .clk(clk),
        .RegWrite(RegWrite),
        .A3(rd),
        .WD3(WD3),
        .A1(rs1),
        .RD1(RD1),
        .A2(rs2),
        .RD2(RD2),
        .dbg_x1(rf_dbg_x1),   // this is your added debug port
        .dbg_x2(rf_dbg_x2),
        .dbg_x3(rf_dbg_x3)
    );

    /* =====================
       Immediate Generation
    ====================== */
    wire [15:0] imm_ext;

    Sign_Extender SE (
        .instr(instruction),
        .ImmSrc(ImmSrc),
        .ImmExt(imm_ext)
    );

    /* =====================
       Execute Stage
    ====================== */
    wire [15:0] ALU_B;
    wire [15:0] ALUResult;

    ALUSrc_mux RD_2 (
        .RD2(RD2),
        .ImmExt(imm_ext),
        .ALUSrc(ALUSrc),
        .SrcB(ALU_B)
    );


    ALU ALU_CORE (
        .SrcA(RD1),
        .SrcB(ALU_B),
        .ALU_control(ALUControl),
        .ALU_result(ALUResult),
        .zero(zero)
    );

    /* =====================
       Data Memory
    ====================== */
    wire [15:0] ReadData;

    Data_Memory DMEM (
        .clk(clk),
        .mem_access_addr(ALUResult),
        .mem_write_data(RD2),
        .mem_write_en(MemWrite),
        .mem_read(ResultSrc),
        .mem_read_data(ReadData)
    );

    /* =====================
       Writeback
    ====================== */
    // Replace WB_MUX module with a simple assign so it works now
    assign WD3 = (ResultSrc) ? ReadData : ALUResult;

    /* =====================
       PC Update Logic
    ====================== */
    // Keep these signals for naming consistency with your skeleton,
    // but they are not currently feeding pc_counter_16 (see note above).
    assign PC_target = PC + imm_ext;
    assign PC_next   = (PCSrc) ? PC_target : PC_plus2;

    /* =====================
       Debug
    ====================== */
    assign dbg_pc         = PC;
    assign dbg_instr      = instruction;
    assign dbg_alu_result = ALUResult;
    assign dbg_x1         = rf_dbg_x1;
    assign dbg_x2         = rf_dbg_x2;
    assign dbg_x3         = rf_dbg_x3;

endmodule

riscv-16/tb/top_tb.v
`timescale 1ns / 1ps

`define STRLEN 32
`define HALF_CLOCK_PERIOD 5
`define CLOCK_PERIOD (`HALF_CLOCK_PERIOD * 2)

module top_tb;

    // Clock and reset
    reg clk;
    reg reset;

    // Debug outputs from DUT
    wire [15:0] dbg_pc;
    wire [15:0] dbg_instr;
    wire [15:0] dbg_alu_result;
    wire [15:0] dbg_x1;
    wire [15:0] dbg_x2;
    wire [15:0] dbg_x3;

    //print IMEM contents at the beginning of the simulation
    initial 
        begin
            #1;
            $display("IMEM[0]=%h", dut.IMEM.memory[0]);
            $display("IMEM[1]=%h", dut.IMEM.memory[1]);
        end


    // Instantiate DUT
    riscv16_top dut (
        .clk(clk),
        .reset(reset),
        .dbg_pc(dbg_pc),
        .dbg_instr(dbg_instr),
        .dbg_alu_result(dbg_alu_result),
        .dbg_x1(dbg_x1),
        .dbg_x2(dbg_x2),
        .dbg_x3(dbg_x3)
    );

    // Waveform dump
    initial begin
        $dumpfile("./tb/waveform/top.vcd");
        $dumpvars(0, top_tb);
    end

    // Clock generation
    initial begin
        clk = 1'b0;
    end
    always begin
        #`HALF_CLOCK_PERIOD clk = ~clk;
    end

    // Simple pass/fail tracking
    reg  [7:0] passed;

    task passTest;
        input [15:0] actualOut;
        input [15:0] expectedOut;
        input [`STRLEN*8:0] testName;
        inout [7:0] passed;
        begin
            if (actualOut === expectedOut) begin
                $display("%s passed (0x%04h)", testName, actualOut);
                passed = passed + 1;
            end else begin
                $display("%s FAILED: got 0x%04h, expected 0x%04h",
                         testName, actualOut, expectedOut);
            end
        end
    endtask

    task allPassed;
        input [7:0] passed;
        input [7:0] numTests;
        begin
            if (passed == numTests)
                $display("All %0d tests passed.", numTests);
            else
                $display("Some tests failed: %0d of %0d passed.", passed, numTests);
        end
    endtask

    // Watchdog
    reg [15:0] watchdog;

    // Number of instructions in program16.mem
    localparam PROGRAM_WORDS = 20;


    // Main stimulus
    initial begin
        passed   = 0;
        watchdog = 0;

        // 1. Reset
        reset = 1'b1;
        #10;
        @(posedge clk);
        #1;             // Small delay to move away from the edge
        reset = 1'b0;   

        $display("--- Starting Execution ---");



        // 2. Monitoring Loop
        while ((dbg_pc >> 1) < PROGRAM_WORDS && watchdog < 100) begin
            @(negedge clk);
            $display("Time=%0t | PC=0x%04h | Instr=0x%04h | ALU=0x%04h | x1=0x%010h | x2=0x%010h | x3=0x%010h",
                    $time, dbg_pc, dbg_instr, dbg_alu_result, dbg_x1, dbg_x2, dbg_x3);

            watchdog = watchdog + 1;
        end

        // 3. Final Check
        $display("--- Simulation Finished ---");
        passTest(dbg_x1, 16'h0004, "Program 1: x1 = 3 + 1", passed);

        allPassed(passed, 1);
        $finish;
    end

endmodule

riscv-16/tb/waveform/top.vcd
$date
	Sat Feb 21 13:39:23 2026
$end
$version
	Icarus Verilog
$end
$timescale
	1ps
$end
$scope module top_tb $end
$var wire 16 ! dbg_x3 [15:0] $end
$var wire 16 " dbg_x2 [15:0] $end
$var wire 16 # dbg_x1 [15:0] $end
$var wire 16 $ dbg_pc [15:0] $end
$var wire 16 % dbg_instr [15:0] $end
$var wire 16 & dbg_alu_result [15:0] $end
$var parameter 32 ' PROGRAM_WORDS $end
$var reg 1 ( clk $end
$var reg 8 ) passed [7:0] $end
$var reg 1 * reset $end
$var reg 16 + watchdog [15:0] $end
$scope module dut $end
$var wire 1 ( clk $end
$var wire 16 , dbg_alu_result [15:0] $end
$var wire 16 - dbg_instr [15:0] $end
$var wire 16 . dbg_pc [15:0] $end
$var wire 16 / dbg_x1 [15:0] $end
$var wire 16 0 dbg_x2 [15:0] $end
$var wire 16 1 dbg_x3 [15:0] $end
$var wire 1 * reset $end
$var wire 16 2 rf_dbg_x1 [15:0] $end
$var wire 16 3 rf_dbg_x2 [15:0] $end
$var wire 16 4 rf_dbg_x3 [15:0] $end
$var wire 1 5 zero $end
$var wire 3 6 rs2_s [2:0] $end
$var wire 3 7 rs2_r [2:0] $end
$var wire 3 8 rs2_b [2:0] $end
$var wire 3 9 rs2 [2:0] $end
$var wire 3 : rs1_s [2:0] $end
$var wire 3 ; rs1_r [2:0] $end
$var wire 3 < rs1_i [2:0] $end
$var wire 3 = rs1_b [2:0] $end
$var wire 3 > rs1 [2:0] $end
$var wire 3 ? rd_u [2:0] $end
$var wire 3 @ rd_r [2:0] $end
$var wire 3 A rd_j [2:0] $end
$var wire 3 B rd_i [2:0] $end
$var wire 3 C rd [2:0] $end
$var wire 3 D opcode [2:0] $end
$var wire 16 E instruction [15:0] $end
$var wire 10 F imm_u_raw [9:0] $end
$var wire 16 G imm_u [15:0] $end
$var wire 7 H imm_s_raw [6:0] $end
$var wire 16 I imm_s [15:0] $end
$var wire 10 J imm_j_raw [9:0] $end
$var wire 16 K imm_j [15:0] $end
$var wire 6 L imm_i_raw [5:0] $end
$var wire 16 M imm_i [15:0] $end
$var wire 16 N imm_ext [15:0] $end
$var wire 4 O imm_b_lo [3:0] $end
$var wire 3 P imm_b_hi [2:0] $end
$var wire 16 Q imm_b [15:0] $end
$var wire 16 R imm [15:0] $end
$var wire 4 S func [3:0] $end
$var wire 16 T WD3 [15:0] $end
$var wire 1 U ResultSrc $end
$var wire 1 V RegWrite $end
$var wire 16 W ReadData [15:0] $end
$var wire 16 X RD2 [15:0] $end
$var wire 16 Y RD1 [15:0] $end
$var wire 16 Z PC_target [15:0] $end
$var wire 16 [ PC_plus2 [15:0] $end
$var wire 16 \ PC_next [15:0] $end
$var wire 1 ] PCSrc $end
$var wire 16 ^ PC [15:0] $end
$var wire 1 _ MemWrite $end
$var wire 3 ` ImmSrc [2:0] $end
$var wire 16 a ALU_B [15:0] $end
$var wire 1 b ALUSrc $end
$var wire 16 c ALUResult [15:0] $end
$var wire 4 d ALUControl [3:0] $end
$var parameter 3 e OPC_B $end
$var parameter 3 f OPC_I $end
$var parameter 3 g OPC_J $end
$var parameter 3 h OPC_R $end
$var parameter 3 i OPC_S $end
$var parameter 3 j OPC_U $end
$scope module ALU_CORE $end
$var wire 1 5 zero $end
$var wire 16 k SrcB [15:0] $end
$var wire 16 l SrcA [15:0] $end
$var wire 4 m ALU_control [3:0] $end
$var reg 16 n ALU_result [15:0] $end
$upscope $end
$scope module CU $end
$var wire 4 o func [3:0] $end
$var wire 3 p opcode [2:0] $end
$var wire 1 5 zero $end
$var reg 4 q ALUControl [3:0] $end
$var reg 1 b ALUSrc $end
$var reg 3 r ImmSrc [2:0] $end
$var reg 1 _ MemWrite $end
$var reg 1 ] PCSrc $end
$var reg 1 V RegWrite $end
$var reg 1 U ResultSrc $end
$upscope $end
$scope module DMEM $end
$var wire 1 ( clk $end
$var wire 16 s mem_access_addr [15:0] $end
$var wire 1 U mem_read $end
$var wire 1 _ mem_write_en $end
$var wire 16 t mem_write_data [15:0] $end
$var wire 16 u mem_read_data [15:0] $end
$var wire 3 v addr [2:0] $end
$upscope $end
$scope module IMEM $end
$var wire 1 ( clk $end
$var wire 16 w word_index [15:0] $end
$var wire 16 x pc [15:0] $end
$var parameter 32 y IMEM_WORDS $end
$var parameter 136 z MEMFILE $end
$var reg 16 { instruction [15:0] $end
$var integer 32 | i [31:0] $end
$upscope $end
$scope module PC_REG $end
$var wire 7 } branch_imm [6:0] $end
$var wire 1 ~ branch_taken $end
$var wire 1 ( clk $end
$var wire 10 !" jal_imm [9:0] $end
$var wire 1 "" jal_taken $end
$var wire 1 #" jalr_taken $end
$var wire 16 $" jalr_target [15:0] $end
$var wire 1 %" pc_en $end
$var wire 1 * reset $end
$var reg 16 &" pc [15:0] $end
$scope function hw_to_bytes $end
$var reg 16 '" imm_hw [15:0] $end
$upscope $end
$upscope $end
$scope module RD_2 $end
$var wire 1 b ALUSrc $end
$var wire 16 (" SrcB [15:0] $end
$var wire 16 )" RD2 [15:0] $end
$var wire 16 *" ImmExt [15:0] $end
$upscope $end
$scope module RF $end
$var wire 3 +" A1 [2:0] $end
$var wire 3 ," A2 [2:0] $end
$var wire 3 -" A3 [2:0] $end
$var wire 1 V RegWrite $end
$var wire 16 ." WD3 [15:0] $end
$var wire 1 ( clk $end
$var wire 16 /" dbg_x1 [15:0] $end
$var wire 16 0" dbg_x2 [15:0] $end
$var wire 16 1" dbg_x3 [15:0] $end
$var wire 16 2" RD2 [15:0] $end
$var wire 16 3" RD1 [15:0] $end
$var integer 32 4" i [31:0] $end
$upscope $end
$scope module SE $end
$var wire 3 5" ImmSrc [2:0] $end
$var wire 16 6" instr [15:0] $end
$var reg 16 7" ImmExt [15:0] $end
$upscope $end
$upscope $end
$scope task allPassed $end
$var reg 8 8" numTests [7:0] $end
$var reg 8 9" passed [7:0] $end
$upscope $end
$scope task passTest $end
$var reg 16 :" actualOut [15:0] $end
$var reg 16 ;" expectedOut [15:0] $end
$var reg 8 <" passed [7:0] $end
$var reg 257 =" testName [256:0] $end
$upscope $end
$upscope $end
$enddefinitions $end
$comment Show the parameter values. $end
$dumpall
b111001101110010011000110010111101110000011100100110111101100111011100100110000101101101001100010011011000101110011011010110010101101101 z
b100000000 y
b110 j
b10 i
b0 h
b100 g
b1 f
b11 e
b10100 '
$end
#0
$dumpvars
bx ="
bx <"
bx ;"
bx :"
bx 9"
bx 8"
bx 7"
bx 6"
bx 5"
b1000 4"
bx 3"
bx 2"
b0 1"
b0 0"
b0 /"
bx ."
bx -"
bx ,"
bx +"
bx *"
bx )"
bx ("
bx '"
b0 &"
1%"
b0 $"
0#"
0""
b0 !"
0~
b0 }
b100000000 |
bx {
b0 x
b0 w
bx v
bx u
bx t
bx s
bx r
bx q
bx p
bx o
bx n
bx m
bx l
bx k
bx d
bx c
xb
bx a
bx `
x_
b0 ^
x]
bx \
b10 [
bx Z
bx Y
bx X
bx W
xV
xU
bx T
bx S
bx R
bx Q
bx P
bx O
bx N
bx M
bx L
bx K
bx J
bx I
bx H
bx000000 G
bx F
bx E
bx D
bx C
bx B
bx A
bx @
bx ?
bx >
bx =
bx <
bx ;
bx :
bx 9
bx 8
bx 7
bx 6
x5
b0 4
b0 3
b0 2
b0 1
b0 0
b0 /
b0 .
bx -
bx ,
b0 +
1*
b0 )
0(
bx &
bx %
b0 $
b0 #
b0 "
b0 !
$end
#5000
b0 v
b0 T
b0 ."
15
b0 &
b0 ,
b0 c
b0 n
b0 s
b0 a
b0 k
b0 ("
b0 Y
b0 l
b0 3"
b0 X
b0 t
b0 )"
b0 2"
b0 W
b0 u
b10 \
b0 M
b0 >
b0 +"
b0 9
b0 ,"
b0 C
b0 -"
b0 R
1V
b0 `
b0 r
b0 5"
0b
b0 d
b0 m
b0 q
0_
0U
0]
b0 Z
b0 N
b0 *"
b0 7"
b0 A
b0 K
b0 J
b0 ?
b0 G
b0 F
b0 8
b0 =
b0 O
b0 Q
b0 P
b0 6
b0 :
b0 I
b0 H
b0 B
b0 <
b0 L
b0 @
b0 7
b0 ;
b0 S
b0 o
b0 D
b0 p
b0 %
b0 -
b0 E
b0 {
b0 6"
1(
#10000
0(
#15000
1(
#16000
0*
#20000
b1 +
0(
#25000
b1 w
b100 \
b10 Z
b100 [
b10 $
b10 .
b10 ^
b10 x
b10 &"
1(
#30000
b10 +
0(
#35000
b100000000 T
b100000000 ."
b100000000 R
05
b100000000 &
b100000000 ,
b100000000 c
b100000000 n
b100000000 s
b1 C
b1 -"
b100000000 a
b100000000 k
b100000000 ("
b100000000 N
b100000000 *"
b100000000 7"
b100 `
b100 r
b100 5"
1b
1V
b1 A
b100 K
b100 J
b1 ?
b100000000 G
b100 F
b1 8
b100 =
b1 6
b100 :
b10 B
b10 <
b10 @
b1 S
b1 o
b110 D
b110 p
b10 w
b110 \
b100001110 %
b100001110 -
b100001110 E
b100001110 {
b100001110 6"
b100000100 Z
b110 [
b100 $
b100 .
b100 ^
b100 x
b100 &"
1(
#40000
b11 +
0(
#45000
b1000000000000000 R
b1000000000000000 T
b1000000000000000 ."
b10 C
b10 -"
b1000000000000000 &
b1000000000000000 ,
b1000000000000000 c
b1000000000000000 n
b1000000000000000 s
b1000000000000000 a
b1000000000000000 k
b1000000000000000 ("
b100000 M
1V
b100 `
b100 r
b100 5"
1b
b1000000000000000 N
b1000000000000000 *"
b1000000000000000 7"
b10 A
b1111111000000000 K
b1000000000 J
b10 ?
b1000000000000000 G
b1000000000 F
b10 8
b0 =
b1111111111000000 Q
b100 P
b10 6
b0 :
b1111111111000000 I
b1000000 H
b0 B
b0 <
b100000 L
b0 @
b100 ;
b10 S
b10 o
b11 w
b1000 \
b1000000000010110 %
b1000000000010110 -
b1000000000010110 E
b1000000000010110 {
b1000000000010110 6"
b100000000 #
b100000000 /
b100000000 2
b100000000 /"
b1000000000000110 Z
b1000 [
b110 $
b110 .
b110 ^
b110 x
b110 &"
1(
#50000
b100 +
0(
