riscv-16/Parameter.v
`ifndef PARAMETER_H_
`define PARAMETER_H_

`define col   16
`define row_d 8

`endif

riscv-16/Data_Memory.v
`include "Parameter.v"
// Verilog-2001 SRAM-like Data Memory (flip-flop implementation)
// Uses Parameter.v: `col = 16, `row_d = 8

module Data_Memory(
  input         clk,
  input  [15:0] mem_access_addr,  // byte address; word index uses [3:1]
  input  [15:0] mem_write_data,
  input         mem_write_en,
  input         mem_read,
  output [15:0] mem_read_data
);
  // Memory array: 8 words x 16 bits (from `row_d and `col)
  reg [`col-1:0] memory [0:`row_d-1];

  // Word-aligned index (drop bit0). With `row_d=8, index width = 3 bits.
  wire [2:0] addr = mem_access_addr[3:1];

  // Synchronous write
  always @(posedge clk) begin
    if (mem_write_en)
      memory[addr] <= mem_write_data;
  end

  // Combinational read with write-first semantics
  assign mem_read_data =
      mem_read
        ? (mem_write_en ? mem_write_data : memory[addr])
        : 16'h0000;

endmodule

riscv-16/tb/Data_Memory_tb.v
`timescale 1ns/1ps

module Data_memory_tb;
  reg         clk;
  reg  [15:0] mem_access_addr;
  reg  [15:0] mem_write_data;
  reg         mem_write_en;
  reg         mem_read;
  wire [15:0] mem_read_data;

  // Declarations must come before task/function declarations (Icarus compatibility)
  integer i;
  reg [15:0] pat_write;   // pattern for write-only case
  reg [15:0] pat_bypass;  // pattern for bypass (read+write) case

  // Summary capture registers
  reg [15:0] obs_write_only_out;
  reg [15:0] obs_read_only_out;
  reg [15:0] obs_bypass_now_out;
  reg [15:0] obs_bypass_readback_out;

  // DUT (change to Data_Memory if your module name is still Data_Memory)
  Data_Memory dut (
    .clk(clk),
    .mem_access_addr(mem_access_addr),
    .mem_write_data(mem_write_data),
    .mem_write_en(mem_write_en),
    .mem_read(mem_read),
    .mem_read_data(mem_read_data)
  );

  // 100 MHz clock
  initial clk = 1'b0;
  always #5 clk = ~clk;

  // Waveform dump (uncomment to generate VCD)
  initial begin
    $dumpfile("Data_memory.vcd");
    $dumpvars(0, Data_memory_tb);
  end

  task write_word(input [2:0] idx, input [15:0] data);
  begin
    @(negedge clk);
    mem_access_addr <= {12'b0, idx, 1'b0}; // word-aligned: [3:1]=idx
    mem_write_data  <= data;
    mem_write_en    <= 1'b1;
    mem_read        <= 1'b0;
    @(posedge clk);        // write happens here
    @(negedge clk);
    mem_write_en    <= 1'b0;
  end
  endtask

  initial begin
    // init
    mem_access_addr = 16'h0000;
    mem_write_data  = 16'h0000;
    mem_write_en    = 1'b0;
    mem_read        = 1'b0;

    // Small sanity: mem_read=0 should force output to 0
    @(negedge clk);
    #1;
    if (mem_read_data !== 16'h0000)
      $display("FAIL init: mem_read_data=%h (expected 0000)", mem_read_data);
    else
      $display("OK   init: mem_read=0 -> mem_read_data=0000");

    // Test ALL addresses 0..7
    for (i = 0; i < 8; i = i + 1) begin
      // ===================== separator =====================
      $display("\n========================================");
      $display("          TESTING ADDRESS %0d", i);
      $display("========================================");

      pat_write  = 16'h1000 + i;  // unique pattern per addr
      pat_bypass = 16'h2000 + i;

      // Clear summary captures
      obs_write_only_out      = 16'hxxxx;
      obs_read_only_out       = 16'hxxxx;
      obs_bypass_now_out      = 16'hxxxx;
      obs_bypass_readback_out = 16'hxxxx;

      // -------------------------------------------------
      // CASE 1: mem_write_en=1, mem_read=0  (write-only)
      // -------------------------------------------------
      @(negedge clk);
      mem_access_addr <= {12'b0, i[2:0], 1'b0}; // word-aligned, [3:1]=i
      mem_write_data  <= pat_write;
      mem_write_en    <= 1'b1;
      mem_read        <= 1'b0;

      #1;
      obs_write_only_out = mem_read_data;

      if (mem_read_data !== 16'h0000)
        $display("FAIL W-only: addr=%0d read=0x%04h exp=0000 @ t=%0t",
                 i, mem_read_data, $time);
      else
        $display("OK   W-only: addr=%0d output=0000", i);

      @(posedge clk);      // commit write
      @(negedge clk);
      mem_write_en <= 1'b0;

      // -------------------------------------------------
      // CASE 2: mem_write_en=0, mem_read=1  (read-only)
      // -------------------------------------------------
      mem_access_addr <= {12'b0, i[2:0], 1'b0};
      mem_write_en    <= 1'b0;
      mem_read        <= 1'b1;

      #1;
      obs_read_only_out = mem_read_data;

      if (mem_read_data !== pat_write)
        $display("FAIL R-only: addr=%0d got=0x%04h exp=0x%04h @ t=%0t",
                 i, mem_read_data, pat_write, $time);
      else
        $display("OK   R-only: addr=%0d data=0x%04h", i, mem_read_data);

      // -------------------------------------------------
      // CASE 3: mem_write_en=1, mem_read=1  (bypass)
      // -------------------------------------------------
      @(negedge clk);
      mem_access_addr <= {12'b0, i[2:0], 1'b0};
      mem_write_data  <= pat_bypass;
      mem_write_en    <= 1'b1;
      mem_read        <= 1'b1;

      #1;
      obs_bypass_now_out = mem_read_data;

      // Expect *bypass* value (new write data)
      if (mem_read_data !== pat_bypass)
        $display("FAIL RW-both (bypass NOW): addr=%0d got=0x%04h exp=0x%04h @ t=%0t",
                 i, mem_read_data, pat_bypass, $time);
      else
        $display("OK   RW-both (bypass NOW): addr=%0d = 0x%04h", i, mem_read_data);

      @(posedge clk);      // commit to memory
      @(negedge clk);
      mem_write_en <= 1'b0;
      mem_read     <= 1'b1;

      #1;
      obs_bypass_readback_out = mem_read_data;

      // After write, reading back should still give pat_bypass
      if (mem_read_data !== pat_bypass)
        $display("FAIL RW-both (read-back): addr=%0d got=0x%04h exp=0x%04h @ t=%0t",
                 i, mem_read_data, pat_bypass, $time);
      else
        $display("OK   RW-both (read-back): addr=%0d = 0x%04h", i, mem_read_data);

      // -------------------------------------------------
      // SUMMARY (new human-readable explanation)
      // -------------------------------------------------
      $display("---- SUMMARY addr=%0d ----", i);
      $display("Wrote 0x%04h in write-only mode (we=1, read=0). Output was 0x%04h because read is disabled.",
               pat_write, obs_write_only_out);
      $display("Then read-only mode (we=0, read=1) returned 0x%04h, confirming the write to this address worked.",
               obs_read_only_out);
      $display("With both enabled (we=1, read=1), tried writing 0x%04h and output immediately showed 0x%04h (bypass/write-through).",
               pat_bypass, obs_bypass_now_out);
      $display("After the clock edge, reading back returned 0x%04h, so the bypass value was stored in memory.",
               obs_bypass_readback_out);
    end

    $display("\nData_Memory test complete.");
    $finish;
  end
endmodule

riscv-16/Data_memory.vcd
$date
	Mon Feb 23 10:20:04 2026
$end
$version
	Icarus Verilog
$end
$timescale
	1ps
$end
$scope module Data_memory_tb $end
$var wire 16 ! mem_read_data [15:0] $end
$var reg 1 " clk $end
$var reg 16 # mem_access_addr [15:0] $end
$var reg 1 $ mem_read $end
$var reg 16 % mem_write_data [15:0] $end
$var reg 1 & mem_write_en $end
$var reg 16 ' obs_bypass_now_out [15:0] $end
$var reg 16 ( obs_bypass_readback_out [15:0] $end
$var reg 16 ) obs_read_only_out [15:0] $end
$var reg 16 * obs_write_only_out [15:0] $end
$var reg 16 + pat_bypass [15:0] $end
$var reg 16 , pat_write [15:0] $end
$var integer 32 - i [31:0] $end
$scope module dut $end
$var wire 1 " clk $end
$var wire 16 . mem_access_addr [15:0] $end
$var wire 1 $ mem_read $end
$var wire 16 / mem_write_data [15:0] $end
$var wire 1 & mem_write_en $end
$var wire 16 0 mem_read_data [15:0] $end
$var wire 3 1 addr [2:0] $end
$upscope $end
$scope task write_word $end
$var reg 16 2 data [15:0] $end
$var reg 3 3 idx [2:0] $end
$upscope $end
$upscope $end
$enddefinitions $end
#0
$dumpvars
bx 3
bx 2
b0 1
b0 0
b0 /
b0 .
bx -
bx ,
bx +
bx *
bx )
bx (
bx '
0&
b0 %
0$
b0 #
0"
b0 !
$end
#5000
1"
#10000
0"
#11000
b10000000000000 +
b1000000000000 ,
b0 -
#15000
1"
#20000
1&
b1000000000000 %
b1000000000000 /
0"
#21000
b0 *
#25000
1"
#30000
b1000000000000 !
b1000000000000 0
1$
0&
0"
#31000
b1000000000000 )
#35000
1"
#40000
b10000000000000 !
b10000000000000 0
1&
b10000000000000 %
b10000000000000 /
0"
#41000
b10000000000000 '
#45000
1"
#50000
0&
0"
#51000
bx '
bx )
bx *
b10000000000001 +
b1000000000001 ,
b1 -
bx (
#55000
1"
#60000
b0 !
b0 0
b1 1
0$
1&
b1000000000001 %
b1000000000001 /
b10 #
b10 .
0"
#61000
b0 *
#65000
1"
#70000
b1000000000001 !
b1000000000001 0
1$
0&
0"
#71000
b1000000000001 )
#75000
1"
#80000
b10000000000001 !
b10000000000001 0
1&
b10000000000001 %
b10000000000001 /
0"
#81000
b10000000000001 '
#85000
1"
#90000
0&
0"
#91000
bx '
bx )
bx *
b10000000000010 +
b1000000000010 ,
b10 -
bx (
#95000
1"
#100000
b0 !
b0 0
b10 1
0$
1&
b1000000000010 %
b1000000000010 /
b100 #
b100 .
0"
#101000
b0 *
#105000
1"
#110000
b1000000000010 !
b1000000000010 0
1$
0&
0"
#111000
b1000000000010 )
#115000
1"
#120000
b10000000000010 !
b10000000000010 0
1&
b10000000000010 %
b10000000000010 /
0"
#121000
b10000000000010 '
#125000
1"
#130000
0&
0"
#131000
bx '
bx )
bx *
b10000000000011 +
b1000000000011 ,
b11 -
bx (
#135000
1"
#140000
b0 !
b0 0
b11 1
0$
1&
b1000000000011 %
b1000000000011 /
b110 #
b110 .
0"
#141000
b0 *
#145000
1"
#150000
b1000000000011 !
b1000000000011 0
1$
0&
0"
#151000
b1000000000011 )
#155000
1"
#160000
b10000000000011 !
b10000000000011 0
1&
b10000000000011 %
b10000000000011 /
0"
#161000
b10000000000011 '
#165000
1"
#170000
0&
0"
#171000
bx '
bx )
bx *
b10000000000100 +
b1000000000100 ,
b100 -
bx (
#175000
1"
#180000
b0 !
b0 0
b100 1
0$
1&
b1000000000100 %
b1000000000100 /
b1000 #
b1000 .
0"
#181000
b0 *
#185000
1"
#190000
b1000000000100 !
b1000000000100 0
1$
0&
0"
#191000
b1000000000100 )
#195000
1"
#200000
b10000000000100 !
b10000000000100 0
1&
b10000000000100 %
b10000000000100 /
0"
#201000
b10000000000100 '
#205000
1"
#210000
0&
0"
#211000
bx '
bx )
bx *
b10000000000101 +
b1000000000101 ,
b101 -
bx (
#215000
1"
#220000
b0 !
b0 0
b101 1
0$
1&
b1000000000101 %
b1000000000101 /
b1010 #
b1010 .
0"
#221000
b0 *
#225000
1"
#230000
b1000000000101 !
b1000000000101 0
1$
0&
0"
#231000
b1000000000101 )
#235000
1"
#240000
b10000000000101 !
b10000000000101 0
1&
b10000000000101 %
b10000000000101 /
0"
#241000
b10000000000101 '
#245000
1"
#250000
0&
0"
#251000
bx '
bx )
bx *
b10000000000110 +
b1000000000110 ,
b110 -
bx (
#255000
1"
#260000
b0 !
b0 0
b110 1
0$
1&
b1000000000110 %
b1000000000110 /
b1100 #
b1100 .
0"
#261000
b0 *
#265000
1"
#270000
b1000000000110 !
b1000000000110 0
1$
0&
0"
#271000
b1000000000110 )
#275000
1"
#280000
b10000000000110 !
b10000000000110 0
1&
b10000000000110 %
b10000000000110 /
0"
#281000
b10000000000110 '
#285000
1"
#290000
0&
0"
#291000
bx '
bx )
bx *
b10000000000111 +
b1000000000111 ,
b111 -
bx (
#295000
1"
#300000
b0 !
b0 0
b111 1
0$
1&
b1000000000111 %
b1000000000111 /
b1110 #
b1110 .
0"
#301000
b0 *
#305000
1"
#310000
b1000000000111 !
b1000000000111 0
1$
0&
0"
#311000
b1000000000111 )
#315000
1"
#320000
b10000000000111 !
b10000000000111 0
1&
b10000000000111 %
b10000000000111 /
0"
#321000
b10000000000111 '
#325000
1"
#330000
0&
0"
#331000
b1000 -
b10000000000111 (
