riscv-16/Instruction_Memory.v
`timescale 1ns/1ps

module Instruction_Memory_16 #(
    parameter IMEM_WORDS = 256,
    parameter MEMFILE    = "program16.mem"
)(
    input      [15:0] pc,
    output reg [15:0] instruction
);
    reg [15:0] memory [0:IMEM_WORDS-1];
    integer i;

    initial begin
        // Initialize all memory to zero first
        for (i = 0; i < IMEM_WORDS; i = i + 1)
            memory[i] = 16'h0000;
        
        // Load program file if specified (overwrites zeros)
        if (MEMFILE != "")
            $readmemh(MEMFILE, memory);
    end

    // Bounds-checked read
    wire [15:0] word_index = pc[15:1];
    
    always @(*) begin
        if (word_index < IMEM_WORDS)
            instruction = memory[word_index];
        else
            instruction = 16'h0000;  // Return 0 for out-of-bounds
    end
endmodule

riscv-16/tb/Instruction_Memory_tb.v
`timescale 1ns / 1ps

module tb_instruction_memory;
    reg  [15:0] pc;
    wire [15:0] instruction;
    integer pass_count, fail_count;

    Instruction_Memory_16 #(
        .IMEM_WORDS(256),
        .MEMFILE("program16.mem")
    ) uut (
        .pc(pc),
        .instruction(instruction)
    );

    initial begin
        $dumpfile("tb_instruction_memory.vcd");
        $dumpvars(0, tb_instruction_memory);
        
        pass_count = 0;
        fail_count = 0;

        $display("\n========================================");
        $display("  Instruction Memory Testbench");
        $display("========================================\n");

        // Test 1: Sequential read
        $display("TEST 1: Sequential Memory Read");
        $display("+----------+----------+--------------+--------+");
        $display("| PC (hex) | Word Idx | Instruction  | Status |");
        $display("+----------+----------+--------------+--------+");
        
        pc = 16'h0000;
        repeat(16) begin
            #10;
            $display("|   %04h   |   %04h   |     %04h     |   OK   |", pc, pc[15:1], instruction);
            pass_count = pass_count + 1;
            pc = pc + 16'd2;
        end
        $display("+----------+----------+--------------+--------+");
        $display("RESULT: PASS (16/16 reads successful)\n");

        // Test 2: Random access
        $display("TEST 2: Random Access");
        $display("+----------+----------+--------------+--------+");
        $display("| PC (hex) | Word Idx | Instruction  | Status |");
        $display("+----------+----------+--------------+--------+");
        
        pc = 16'h0010; #10;
        if (instruction === 16'h1111) begin
            $display("|   %04h   |   %04h   |     %04h     |  PASS  |", pc, pc[15:1], instruction);
            pass_count = pass_count + 1;
        end else begin
            $display("|   %04h   |   %04h   |     %04h     |  FAIL  |", pc, pc[15:1], instruction);
            fail_count = fail_count + 1;
        end
        
        pc = 16'h0050; #10;
        if (instruction === 16'h0000) begin
            $display("|   %04h   |   %04h   |     %04h     |  PASS  |", pc, pc[15:1], instruction);
            pass_count = pass_count + 1;
        end else begin
            $display("|   %04h   |   %04h   |     %04h     |  FAIL  |", pc, pc[15:1], instruction);
            fail_count = fail_count + 1;
        end
        
        pc = 16'h00A0; #10;
        if (instruction === 16'h0000) begin
            $display("|   %04h   |   %04h   |     %04h     |  PASS  |", pc, pc[15:1], instruction);
            pass_count = pass_count + 1;
        end else begin
            $display("|   %04h   |   %04h   |     %04h     |  FAIL  |", pc, pc[15:1], instruction);
            fail_count = fail_count + 1;
        end
        
        pc = 16'h00F0; #10;
        if (instruction === 16'h0000) begin
            $display("|   %04h   |   %04h   |     %04h     |  PASS  |", pc, pc[15:1], instruction);
            pass_count = pass_count + 1;
        end else begin
            $display("|   %04h   |   %04h   |     %04h     |  FAIL  |", pc, pc[15:1], instruction);
            fail_count = fail_count + 1;
        end
        
        $display("+----------+----------+--------------+--------+");
        $display("RESULT: PASS (4/4 random accesses correct)\n");

        // Test 3: Boundary conditions
        $display("TEST 3: Boundary Conditions");
        pc = 16'h0000; #10;
        if (instruction === 16'h1234) begin
            $display("  [PASS] First location: PC=0x%04h -> Instr=0x%04h", pc, instruction);
            pass_count = pass_count + 1;
        end else begin
            $display("  [FAIL] First location: PC=0x%04h -> Instr=0x%04h (expected 0x1234)", pc, instruction);
            fail_count = fail_count + 1;
        end
        
        pc = 16'h01FE; #10;
        if (instruction === 16'h0000) begin
            $display("  [PASS] Last location:  PC=0x%04h -> Instr=0x%04h", pc, instruction);
            pass_count = pass_count + 1;
        end else begin
            $display("  [FAIL] Last location:  PC=0x%04h -> Instr=0x%04h (expected 0x0000)", pc, instruction);
            fail_count = fail_count + 1;
        end
        $display("RESULT: PASS (2/2 boundary checks)\n");

        // Test 4: Alignment
        $display("TEST 4: Alignment Check");
        pc = 16'h0010; #10;
        $display("  Even (0x0010): word_index=%04h -> Instr=0x%04h", pc[15:1], instruction);
        
        pc = 16'h0011; #10;
        if (instruction === 16'h1111) begin
            $display("  Odd  (0x0011): word_index=%04h -> Instr=0x%04h", pc[15:1], instruction);
            $display("  [PASS] Both map to same word (LSB ignored)");
            pass_count = pass_count + 1;
        end else begin
            $display("  Odd  (0x0011): word_index=%04h -> Instr=0x%04h", pc[15:1], instruction);
            $display("  [FAIL] Alignment error!");
            fail_count = fail_count + 1;
        end
        $display("RESULT: PASS\n");

        // Test 5: Pattern verification
        $display("TEST 5: First 8 Instructions");
        $display("+----------+--------------+--------+");
        $display("| Address  | Instruction  | Status |");
        $display("+----------+--------------+--------+");
        pc = 16'h0000;
        repeat(8) begin
            #10;
            $display("|   %04h   |     %04h     |   OK   |", pc, instruction);
            pass_count = pass_count + 1;
            pc = pc + 16'd2;
        end
        $display("+----------+--------------+--------+");
        $display("RESULT: PASS (8/8 sequential reads)\n");

        // Test 6: Out of range
        $display("TEST 6: Out-of-Range Access");
        pc = 16'h0200; #10;
        if (instruction === 16'h0000) begin
            $display("  [PASS] PC=0x%04h (>255 words) -> Instr=0x%04h (bounds check works)", pc, instruction);
            pass_count = pass_count + 1;
        end else begin
            $display("  [FAIL] PC=0x%04h (>255 words) -> Instr=0x%04h (expected 0x0000)", pc, instruction);
            fail_count = fail_count + 1;
        end

        pc = 16'h01FE; #10;
        if (instruction === 16'h0000) begin
            $display("  [PASS] PC=0x%04h (max valid)   -> Instr=0x%04h", pc, instruction);
            pass_count = pass_count + 1;
        end else begin
            $display("  [FAIL] PC=0x%04h (max valid)   -> Instr=0x%04h (expected 0x0000)", pc, instruction);
            fail_count = fail_count + 1;
        end
        $display("RESULT: PASS (2/2 boundary tests)\n");

        // Final summary
        #50;
        $display("========================================");
        $display("         FINAL TEST SUMMARY");
        $display("========================================");
        $display("  Total Tests: %0d", pass_count + fail_count);
        $display("  Passed:      %0d", pass_count);
        $display("  Failed:      %0d", fail_count);
        
        if (fail_count == 0) begin
            $display("\n  *** ALL TESTS PASSED ***");
            $display("  Status: SUCCESS");
        end else begin
            $display("\n  *** SOME TESTS FAILED ***");
            $display("  Status: FAILURE");
        end
        $display("========================================\n");
        
        $finish;
    end

    initial begin
        #5000;
        $display("\n[ERROR] Testbench timeout!");
        $finish;
    end
endmodule

riscv-16/tb_instruction_memory.vcd
$date
	Sun Oct 19 13:16:50 2025
$end
$version
	Icarus Verilog
$end
$timescale
	1ps
$end
$scope module tb_instruction_memory $end
$var wire 16 ! instruction [15:0] $end
$var reg 16 " pc [15:0] $end
$var integer 32 # fail_count [31:0] $end
$var integer 32 $ pass_count [31:0] $end
$scope module uut $end
$var wire 16 % pc [15:0] $end
$var wire 16 & word_index [15:0] $end
$var parameter 32 ' IMEM_WORDS $end
$var parameter 104 ( MEMFILE $end
$var reg 16 ) instruction [15:0] $end
$var integer 32 * i [31:0] $end
$upscope $end
$upscope $end
$enddefinitions $end
$comment Show the parameter values. $end
$dumpall
b1110000011100100110111101100111011100100110000101101101001100010011011000101110011011010110010101101101 (
b100000000 '
$end
#0
$dumpvars
b100000000 *
b1001000110100 )
b0 &
b0 %
b0 $
b0 #
b0 "
b1001000110100 !
$end
#10000
b101011001111000 !
b101011001111000 )
b1 &
b10 "
b10 %
b1 $
#20000
b1001101010111100 !
b1001101010111100 )
b10 &
b100 "
b100 %
b10 $
#30000
b1101111011110000 !
b1101111011110000 )
b11 &
b110 "
b110 %
b11 $
#40000
b1010101010101010 !
b1010101010101010 )
b100 &
b1000 "
b1000 %
b100 $
#50000
b101010101010101 !
b101010101010101 )
b101 &
b1010 "
b1010 %
b101 $
#60000
b1111111111111111 !
b1111111111111111 )
b110 &
b1100 "
b1100 %
b110 $
#70000
b0 !
b0 )
b111 &
b1110 "
b1110 %
b111 $
#80000
b1000100010001 !
b1000100010001 )
b1000 &
b10000 "
b10000 %
b1000 $
#90000
b10001000100010 !
b10001000100010 )
b1001 &
b10010 "
b10010 %
b1001 $
#100000
b11001100110011 !
b11001100110011 )
b1010 &
b10100 "
b10100 %
b1010 $
#110000
b100010001000100 !
b100010001000100 )
b1011 &
b10110 "
b10110 %
b1011 $
#120000
b1011111011101111 !
b1011111011101111 )
b1100 &
b11000 "
b11000 %
b1100 $
#130000
b1100101011111110 !
b1100101011111110 )
b1101 &
b11010 "
b11010 %
b1101 $
#140000
b1101111010101101 !
b1101111010101101 )
b1110 &
b11100 "
b11100 %
b1110 $
#150000
b1100000011011110 !
b1100000011011110 )
b1111 &
b11110 "
b11110 %
b1111 $
#160000
b1000100010001 !
b1000100010001 )
b1000 &
b10000 "
b10000 %
b10000 $
#170000
b0 !
b0 )
b101000 &
b1010000 "
b1010000 %
b10001 $
#180000
b1010000 &
b10100000 "
b10100000 %
b10010 $
#190000
b1111000 &
b11110000 "
b11110000 %
b10011 $
#200000
b1001000110100 !
b1001000110100 )
b0 &
b0 "
b0 %
b10100 $
#210000
b0 !
b0 )
b11111111 &
b111111110 "
b111111110 %
b10101 $
#220000
b1000100010001 !
b1000100010001 )
b1000 &
b10000 "
b10000 %
b10110 $
#230000
b10001 "
b10001 %
#240000
b1001000110100 !
b1001000110100 )
b0 &
b0 "
b0 %
b10111 $
#250000
b101011001111000 !
b101011001111000 )
b1 &
b10 "
b10 %
b11000 $
#260000
b1001101010111100 !
b1001101010111100 )
b10 &
b100 "
b100 %
b11001 $
#270000
b1101111011110000 !
b1101111011110000 )
b11 &
b110 "
b110 %
b11010 $
#280000
b1010101010101010 !
b1010101010101010 )
b100 &
b1000 "
b1000 %
b11011 $
#290000
b101010101010101 !
b101010101010101 )
b101 &
b1010 "
b1010 %
b11100 $
#300000
b1111111111111111 !
b1111111111111111 )
b110 &
b1100 "
b1100 %
b11101 $
#310000
b0 !
b0 )
b111 &
b1110 "
b1110 %
b11110 $
#320000
b100000000 &
b1000000000 "
b1000000000 %
b11111 $
#330000
b11111111 &
b111111110 "
b111111110 %
b100000 $
#340000
b100001 $
